{"bike":{"frame_model":"Suede DX W (Black/ Silver)","manufacturer":"Giant","year":2011,"description":"ALUXX-Grade Aluminum","original_paints":["Black/Silver, Pearl White/Light Blue"],"sizes":["Regular, Large"],"msrp":"$460","stock_image":"https://bikebook.s3.amazonaws.com/uploads/Fr/7951/Suede_DX_w_black_72dpiWIDE.jpg"},"components":[{"ctype":"fork","description":"RST SOFI 'T', 63mm Travel"},{"ctype":"handlebars","description":"Steel, Mid Rise, 25.4"},{"ctype":"stem","description":"Alloy"},{"ctype":"seatpost","description":"Alloy, 30.9"},{"ctype":"saddle","description":"Giant Comfort Cruiser Gel W, SuperSoft"},{"ctype":"pedals","description":"Translucent Comfort Platform"},{"ctype":"shifter","description":"SRAM 3.0 Comp, Twist","front_or_rear":"both"},{"ctype":"derailleur","description":"Shimano Alivo, E-Type","front_or_rear":"front"},{"ctype":"derailleur","description":"SRAM X.3","front_or_rear":"rear"},{"ctype":"brake","description":"Alloy, Direct-Pull","front_or_rear":"both"},{"ctype":"brake lever","description":"Alloy, Comfort","front_or_rear":"both"},{"ctype":"cog/cassette/freewheel","description":"SRAM PG730 12x32, 7-Speed"},{"ctype":"chain","description":"KMC Z51"},{"ctype":"crankset","description":"Alloy 3-Piece, 22/32/42"},{"ctype":"bottom bracket","description":"Sealed Cartridge"},{"ctype":"rim","description":"Alloy","front_or_rear":"both"},{"ctype":"hub","description":"Alloy, 32h","front_or_rear":"both"},{"ctype":"spokes","description":"Stainless Steel"},{"ctype":"tire","description":"Kenda, 26x1.95","front_or_rear":"both"},{"ctype":"other","description":"Kickstand"},{"ctype":"weight","description":"The most accurate way to determine any bike’s weight is to have your local dealer weigh it for you. Many brands strive to list the lowest possible weight, but in reality weight can vary based on size, finish, hardware and accessories. All Giant bikes are designed for best-in-class weight and ride quality."}]}