{"bike":{"frame_model":"Stumpjumper FSR Pro","manufacturer":"Specialized","year":2007,"description":"FSR M5 manipulated alloy frame w/ Transform monocoque TT, Magnesium link, carbon reservoir mount, sealed cartridge bearing pivots and rear shock mounts. replaceable derailleur hanger, two sets of water bottle bosses, disc compatible, 120mm travel","paint_description":"Black Ano","rear_wheel_bsd":559,"stock_photo_url":"https://bikebook.s3.amazonaws.com/uploads/Fr/5404/SJ_FSR_Pro_Blk_Ano.jpg"},"components":[{"component_type":"rear suspension","description":"Specialized AFR Shock w/ Flow Control valve, adjustable Trail Tune range, air spring, adjustable rebound, 7.75x1.75\""},{"component_type":"fork","description":"Fox Talas RLC, 100-140mm, rebound adj, alloy steerer"},{"component_type":"headset","description":"1 1/8\" Threadless, alloy cups w/ 10mm insertion, sealed cartridge bearing"},{"component_type":"stem","description":"Specialized adjustable rise, OS 31.8, 3D forged w/CNC finish"},{"component_type":"handlebar","description":"SBC OS XC low rise carbon bar, 640mm wide, 6 degree up, 8 degree backsweep"},{"component_type":"grips/tape","description":"Specialized MTB, dual density"},{"component_type":"brake","description":"Magura Marta, hydraulic disc, S/M: 180mm rotor, L/XL: 200mm rotor","front_or_rear":"front"},{"component_type":"brake","description":"Magura Marta, hydraulic disc, S/M: 160mm rotor, L/XL: 180mm rotor","front_or_rear":"rear"},{"component_type":"brake lever","description":"Magura Marta","front_or_rear":"both"},{"component_type":"derailleur","description":"Shimano M760 XT, 34.9 clamp, bottom swing, dual pull","front_or_rear":"front"},{"component_type":"derailleur","description":"SRAM X.0, 9-speed, long cage","front_or_rear":"rear"},{"component_type":"shifter","description":"SRAM X.0, carbon/aluminum trigger 9-speed","front_or_rear":"both"},{"component_type":"cog/cassette/freewheel","description":"Shimano M760 XT, 9-speed, 11/34t"},{"component_type":"chain","description":"SRAM PC-951 w /Power Link"},{"component_type":"crankset","description":"Shimano M-760 XT Hollowtech II, 2pc crank/BB"},{"component_type":"chainrings","description":"22A/32A/44A 4mm thick outer, 4 bolt 104/64mm"},{"component_type":"bottom bracket","description":"Shimano M-760 XT, integrated with crank"},{"component_type":"pedals","description":"Shimano M-520 SPD"},{"component_type":"rim","description":"DT Swiss XR 4.2D, 24mm w/ eyelets, 32h","front_or_rear":"both"},{"component_type":"hub","description":"Specialized Stout disc, sealed cartridge bearing, high/low flange, 32h","front_or_rear":"front"},{"component_type":"hub","description":"DT Swiss Custom SL, 32h disc, alloy QR","front_or_rear":"rear"},{"component_type":"spokes","description":"DT Swiss Super Comp 2.0/1.7/1.8 stainless, alloy nipples"},{"component_type":"tire","description":"Specialized Resolution Pro 26x2.1\", 120TPI, aramid bead, dual compound","front_or_rear":"front"},{"component_type":"tire","description":"Specialized Resolution Pro 26x2.1\", 120TPI, aramid bead, dual compound","front_or_rear":"rear"},{"component_type":"tube","description":"Specialized Ultralight 26x2.0\", presta","front_or_rear":"both"},{"component_type":"saddle","description":"Specialized BG Rival, Titanium rails"},{"component_type":"seatpost","description":"Thomson, 7000 series aluminum, 2-bolt adjust, 30.9mm x 367/410mm"},{"component_type":"seatpost clamp","description":"7050 hard annodized alloy collar w/ QR, 34.9mm clamp ID, black"},{"component_type":"other","description":"Protective clear coat, derailleur hanger, reflectors, owners manual"}]}