{"bike":{"frame_model":"Quadangle Looptail (Frameset)","manufacturer":"SE Bikes","year":2008,"manufacturers_url":"http://www.sebikes.com/archive/2008/quadangle-looptail-frameset2","stock_photo_url":"https://bikebook.s3.amazonaws.com/uploads/Fr/9138/quadangle-looptail-main-photo-lowres.jpg","stock_photo_small":"https://bikebook.s3.amazonaws.com/uploads/Fr/9138/medium_quadangle-looptail-main-photo-lowres.jpg"},"components":[{"component_type":"quadangle looptail","description":"-100% CR-MO Retro Design -American Bottom Bracket -1-1/8\u00e2\u20ac\u009d Head Tube -Includes Headset, Seat Clamp, & Alloy Rear Wheel Washers-21.3\u00e2\u20ac\u009d TT, 15.20\u00e2\u20ac\u009d CS, 74 Degree HT, 71 Degree ST -5.6 lbs Frame","cgroup":"Additional parts"}]}