[{"id":"absolute_1_0","text":"Absolute 1.0","name":"Absolute 1.0"},{"id":"absolute_2_0","text":"Absolute 2.0","name":"Absolute 2.0"},{"id":"absolute_3_0","text":"Absolute 3.0","name":"Absolute 3.0"},{"id":"absolute_3_0_st","text":"Absolute 3.0 St","name":"Absolute 3.0 St"},{"id":"absolute_4_0","text":"Absolute 4.0","name":"Absolute 4.0"},{"id":"absolute_4_0_st","text":"Absolute 4.0 St","name":"Absolute 4.0 St"},{"id":"absolute_5_0","text":"Absolute 5.0","name":"Absolute 5.0"},{"id":"absolute_5_0_st","text":"Absolute 5.0 St","name":"Absolute 5.0 St"},{"id":"ace_20","text":"Ace 20","name":"Ace 20"},{"id":"ace_24","text":"Ace 24","name":"Ace 24"},{"id":"ace_650","text":"Ace 650","name":"Ace 650"},{"id":"addy_1_0","text":"Addy 1.0","name":"Addy 1.0"},{"id":"addy_2_0","text":"Addy 2.0","name":"Addy 2.0"},{"id":"addy_3_0","text":"Addy 3.0","name":"Addy 3.0"},{"id":"aloha_1_0","text":"Aloha 1.0","name":"Aloha 1.0"},{"id":"aloha_2_0","text":"Aloha 2.0","name":"Aloha 2.0"},{"id":"altamira_1_0","text":"Altamira 1.0","name":"Altamira 1.0"},{"id":"altamira_1_0_di2_da","text":"Altamira 1.0 Di2 Da","name":"Altamira 1.0 Di2 Da"},{"id":"altamira_2_0","text":"Altamira 2.0","name":"Altamira 2.0"},{"id":"altamira_2_0_di2_ul","text":"Altamira 2.0 Di2 Ul","name":"Altamira 2.0 Di2 Ul"},{"id":"altamira_3_0","text":"Altamira 3.0","name":"Altamira 3.0"},{"id":"altamira_cx_1_0","text":"Altamira Cx 1.0","name":"Altamira Cx 1.0"},{"id":"altamira_cx_1_0_frameset","text":"Altamira Cx 1.0 (Frameset)","name":"Altamira Cx 1.0 (Frameset)"},{"id":"altamira_cx_2_0","text":"Altamira Cx 2.0","name":"Altamira Cx 2.0"},{"id":"altamira_di2_le","text":"Altamira Di2 Le","name":"Altamira Di2 Le"},{"id":"altamira_ltd_team_edition","text":"Altamira Ltd Team Edition","name":"Altamira Ltd Team Edition"},{"id":"altamira_ltd_team_edition_frameset","text":"Altamira Ltd Team Edition Frameset","name":"Altamira Ltd Team Edition Frameset"},{"id":"altamira_special_edition_frameset","text":"Altamira Special Edition Frameset","name":"Altamira Special Edition Frameset"},{"id":"altamira_team_replica","text":"Altamira Team Replica","name":"Altamira Team Replica"},{"id":"belle_1_0","text":"Belle 1.0","name":"Belle 1.0"},{"id":"belle_2_0","text":"Belle 2.0","name":"Belle 2.0"},{"id":"betsy","text":"Betsy","name":"Betsy"},{"id":"cape_may","text":"Cape May","name":"Cape May"},{"id":"cape_may_st","text":"Cape May St","name":"Cape May St"},{"id":"captiva","text":"Captiva","name":"Captiva"},{"id":"captiva_st","text":"Captiva St","name":"Captiva St"},{"id":"classic","text":"Classic","name":"Classic"},{"id":"cross_1_0","text":"Cross 1.0","name":"Cross 1.0"},{"id":"cross_2_0","text":"Cross 2.0","name":"Cross 2.0"},{"id":"cross_3_0","text":"Cross 3.0","name":"Cross 3.0"},{"id":"crosstown_1_0","text":"Crosstown 1.0","name":"Crosstown 1.0"},{"id":"crosstown_1_0_ls","text":"Crosstown 1.0 Ls","name":"Crosstown 1.0 Ls"},{"id":"crosstown_2_0","text":"Crosstown 2.0","name":"Crosstown 2.0"},{"id":"crosstown_2_0_ls","text":"Crosstown 2.0 Ls","name":"Crosstown 2.0 Ls"},{"id":"crosstown_3_0","text":"Crosstown 3.0","name":"Crosstown 3.0"},{"id":"crosstown_3_0_ls","text":"Crosstown 3.0 Ls","name":"Crosstown 3.0 Ls"},{"id":"crosstown_4_0","text":"Crosstown 4.0","name":"Crosstown 4.0"},{"id":"crosstown_4_0_ls","text":"Crosstown 4.0 Ls","name":"Crosstown 4.0 Ls"},{"id":"d_6_1_0","text":"D 6 1.0","name":"D 6 1.0"},{"id":"d_6_2_0","text":"D 6 2.0","name":"D 6 2.0"},{"id":"d_6_2_0_frameset","text":"D 6 2.0 (Frameset)","name":"D 6 2.0 (Frameset)"},{"id":"d_6_3_0","text":"D 6 3.0","name":"D 6 3.0"},{"id":"d_6_4_0","text":"D 6 4.0","name":"D 6 4.0"},{"id":"d_6_special_edition_frameset","text":"D 6 Special Edition Frameset","name":"D 6 Special Edition Frameset"},{"id":"declaration","text":"Declaration","name":"Declaration"},{"id":"dynamite_1_0_b","text":"Dynamite 1.0 B","name":"Dynamite 1.0 B"},{"id":"dynamite_1_0_g","text":"Dynamite 1.0 G","name":"Dynamite 1.0 G"},{"id":"dynamite_2_0","text":"Dynamite 2.0","name":"Dynamite 2.0"},{"id":"dynamite_2_0_g","text":"Dynamite 2.0 G","name":"Dynamite 2.0 G"},{"id":"fazer_16","text":"Fazer 16\"","name":"Fazer 16\""},{"id":"fazer_20","text":"Fazer 20\"","name":"Fazer 20\""},{"id":"feather","text":"Feather","name":"Feather"},{"id":"feather_cx","text":"Feather Cx ()","name":"Feather Cx ()"},{"id":"finest_1_0","text":"Finest 1.0","name":"Finest 1.0"},{"id":"finest_2_0","text":"Finest 2.0","name":"Finest 2.0"},{"id":"finest_3_0","text":"Finest 3.0","name":"Finest 3.0"},{"id":"gran_fondo_1_0","text":"Gran Fondo 1.0","name":"Gran Fondo 1.0"},{"id":"gran_fondo_2_0","text":"Gran Fondo 2.0","name":"Gran Fondo 2.0"},{"id":"gran_fondo_2_0_di2_ul","text":"Gran Fondo 2.0 Di2 Ul","name":"Gran Fondo 2.0 Di2 Ul"},{"id":"gran_fondo_3_0","text":"Gran Fondo 3.0","name":"Gran Fondo 3.0"},{"id":"gran_fondo_4_0","text":"Gran Fondo 4.0","name":"Gran Fondo 4.0"},{"id":"kit","text":"Kit","name":"Kit"},{"id":"mio_amore","text":"Mio Amore","name":"Mio Amore"},{"id":"nevada_1_0","text":"Nevada 1.0","name":"Nevada 1.0"},{"id":"nevada_29_1_0","text":"Nevada 29 1.0","name":"Nevada 29 1.0"},{"id":"nevada_29_2_0","text":"Nevada 29 2.0","name":"Nevada 29 2.0"},{"id":"nevada_29_3_0","text":"Nevada 29 3.0","name":"Nevada 29 3.0"},{"id":"nevada_29_4_0","text":"Nevada 29 4.0","name":"Nevada 29 4.0"},{"id":"nevada_2_0","text":"Nevada 2.0","name":"Nevada 2.0"},{"id":"nevada_3_0","text":"Nevada 3.0","name":"Nevada 3.0"},{"id":"nevada_3_0_st","text":"Nevada 3.0 St","name":"Nevada 3.0 St"},{"id":"nevada_4_0","text":"Nevada 4.0","name":"Nevada 4.0"},{"id":"nevada_4_0_st","text":"Nevada 4.0 St","name":"Nevada 4.0 St"},{"id":"nevada_5_0","text":"Nevada 5.0","name":"Nevada 5.0"},{"id":"nevada_5_0_st","text":"Nevada 5.0 St","name":"Nevada 5.0 St"},{"id":"nevada_6_0","text":"Nevada 6.0","name":"Nevada 6.0"},{"id":"nevada_6_0_st","text":"Nevada 6.0 St","name":"Nevada 6.0 St"},{"id":"newest_1_0","text":"Newest 1.0","name":"Newest 1.0"},{"id":"newest_2_0","text":"Newest 2.0","name":"Newest 2.0"},{"id":"newest_3_0","text":"Newest 3.0","name":"Newest 3.0"},{"id":"newest_4_0","text":"Newest 4.0","name":"Newest 4.0"},{"id":"outland_1_0","text":"Outland 1.0","name":"Outland 1.0"},{"id":"outland_1_0_frame","text":"Outland 1.0 Frame","name":"Outland 1.0 Frame"},{"id":"outland_29_1_0","text":"Outland 29 1.0","name":"Outland 29 1.0"},{"id":"outland_29_1_0_frame","text":"Outland 29 1.0 Frame","name":"Outland 29 1.0 Frame"},{"id":"outland_29_2_0","text":"Outland 29 2.0","name":"Outland 29 2.0"},{"id":"outland_29_3_0","text":"Outland 29 3.0","name":"Outland 29 3.0"},{"id":"outland_2_0","text":"Outland 2.0","name":"Outland 2.0"},{"id":"outland_3_0","text":"Outland 3.0","name":"Outland 3.0"},{"id":"police_patrol","text":"Police Patrol","name":"Police Patrol"},{"id":"police_special","text":"Police Special","name":"Police Special"},{"id":"police_special_29","text":"Police Special 29","name":"Police Special 29"},{"id":"porteur","text":"Porteur","name":"Porteur"},{"id":"porteur_st","text":"Porteur St","name":"Porteur St"},{"id":"princess_inari","text":"Princess Inari","name":"Princess Inari"},{"id":"reveal_1_0","text":"Reveal 1.0","name":"Reveal 1.0"},{"id":"reveal_1_0_frameset","text":"Reveal 1.0 (Frameset)","name":"Reveal 1.0 (Frameset)"},{"id":"reveal_2_0","text":"Reveal 2.0","name":"Reveal 2.0"},{"id":"reveal_3_0","text":"Reveal 3.0","name":"Reveal 3.0"},{"id":"roubaix_1_0","text":"Roubaix 1.0","name":"Roubaix 1.0"},{"id":"roubaix_2_0","text":"Roubaix 2.0","name":"Roubaix 2.0"},{"id":"roubaix_3_0","text":"Roubaix 3.0","name":"Roubaix 3.0"},{"id":"roubaix_sl","text":"Roubaix Sl","name":"Roubaix Sl"},{"id":"sagres_1_0","text":"Sagres 1.0","name":"Sagres 1.0"},{"id":"sagres_1_0_ls","text":"Sagres 1.0 Ls","name":"Sagres 1.0 Ls"},{"id":"sagres_2_0","text":"Sagres 2.0","name":"Sagres 2.0"},{"id":"sagres_2_0_ls","text":"Sagres 2.0 Ls","name":"Sagres 2.0 Ls"},{"id":"sagres_3_0","text":"Sagres 3.0","name":"Sagres 3.0"},{"id":"sagres_3_0_ls","text":"Sagres 3.0 Ls","name":"Sagres 3.0 Ls"},{"id":"sagres_4_0","text":"Sagres 4.0","name":"Sagres 4.0"},{"id":"sagres_4_0_ls","text":"Sagres 4.0 Ls","name":"Sagres 4.0 Ls"},{"id":"sandblaster","text":"Sandblaster","name":"Sandblaster"},{"id":"sandblaster_g","text":"Sandblaster G","name":"Sandblaster G"},{"id":"sanibel_1_0","text":"Sanibel 1.0","name":"Sanibel 1.0"},{"id":"sanibel_1_0_ls","text":"Sanibel 1.0 Ls","name":"Sanibel 1.0 Ls"},{"id":"sanibel_24","text":"Sanibel (24\")","name":"Sanibel (24\")"},{"id":"sanibel_24_g","text":"Sanibel 24\" G","name":"Sanibel 24\" G"},{"id":"sanibel_2_0","text":"Sanibel 2.0","name":"Sanibel 2.0"},{"id":"sanibel_2_0_ls","text":"Sanibel 2.0 Ls","name":"Sanibel 2.0 Ls"},{"id":"saratoga_1_0","text":"Saratoga 1.0","name":"Saratoga 1.0"},{"id":"saratoga_1_0_ls","text":"Saratoga 1.0 Ls","name":"Saratoga 1.0 Ls"},{"id":"saratoga_2_0","text":"Saratoga 2.0","name":"Saratoga 2.0"},{"id":"saratoga_2_0_ls","text":"Saratoga 2.0 Ls","name":"Saratoga 2.0 Ls"},{"id":"saratoga_3_0","text":"Saratoga 3.0","name":"Saratoga 3.0"},{"id":"saratoga_3_0_ls","text":"Saratoga 3.0 Ls","name":"Saratoga 3.0 Ls"},{"id":"sl_special_edition_frameset","text":"Sl Special Edition Frameset","name":"Sl Special Edition Frameset"},{"id":"slm_1_0_frameset","text":"Slm 1.0 (Frameset)","name":"Slm 1.0 (Frameset)"},{"id":"slm_29_1_0","text":"Slm 29 1.0","name":"Slm 29 1.0"},{"id":"slm_29_1_0_frameset","text":"Slm 29 1.0 (Frameset)","name":"Slm 29 1.0 (Frameset)"},{"id":"slm_29_2_0","text":"Slm 29 2.0","name":"Slm 29 2.0"},{"id":"slm_29_3_0","text":"Slm 29 3.0","name":"Slm 29 3.0"},{"id":"slm_29_ltd","text":"Slm 29 Ltd","name":"Slm 29 Ltd"},{"id":"sst_1_0","text":"Sst 1.0","name":"Sst 1.0"},{"id":"sst_1_0_frameset","text":"Sst 1.0 (Frameset)","name":"Sst 1.0 (Frameset)"},{"id":"sst_2_0","text":"Sst 2.0","name":"Sst 2.0"},{"id":"sst_2_0_di2_ul","text":"Sst 2.0 Di2 Ul","name":"Sst 2.0 Di2 Ul"},{"id":"sst_3_0","text":"Sst 3.0","name":"Sst 3.0"},{"id":"sst_special_edition_frameset","text":"Sst Special Edition Frameset","name":"Sst Special Edition Frameset"},{"id":"sst_special_edition_frameset_ii","text":"Sst Special Edition Frameset Ii","name":"Sst Special Edition Frameset Ii"},{"id":"sunfire_1_0","text":"Sunfire 1.0","name":"Sunfire 1.0"},{"id":"sunfire_2_0","text":"Sunfire 2.0","name":"Sunfire 2.0"},{"id":"sunfire_3_0","text":"Sunfire 3.0","name":"Sunfire 3.0"},{"id":"sunfire_3_0_st","text":"Sunfire 3.0 St","name":"Sunfire 3.0 St"},{"id":"supreme_1_0","text":"Supreme 1.0","name":"Supreme 1.0"},{"id":"supreme_1_0_frameset","text":"Supreme 1.0 (Frameset)","name":"Supreme 1.0 (Frameset)"},{"id":"supreme_2_0","text":"Supreme 2.0","name":"Supreme 2.0"},{"id":"supreme_3_0","text":"Supreme 3.0","name":"Supreme 3.0"},{"id":"supreme_ltd_team_edition","text":"Supreme Ltd Team Edition","name":"Supreme Ltd Team Edition"},{"id":"supreme_special_edition_frameset","text":"Supreme Special Edition Frameset","name":"Supreme Special Edition Frameset"},{"id":"tahoe_1_0","text":"Tahoe 1.0","name":"Tahoe 1.0"},{"id":"tahoe_29_1_0","text":"Tahoe 29 1.0","name":"Tahoe 29 1.0"},{"id":"tahoe_29_2_0","text":"Tahoe 29 2.0","name":"Tahoe 29 2.0"},{"id":"tahoe_29_3_0","text":"Tahoe 29 3.0","name":"Tahoe 29 3.0"},{"id":"tahoe_29_4_0","text":"Tahoe 29 4.0","name":"Tahoe 29 4.0"},{"id":"tahoe_2_0","text":"Tahoe 2.0","name":"Tahoe 2.0"},{"id":"tahoe_3_0","text":"Tahoe 3.0","name":"Tahoe 3.0"},{"id":"tahoe_4_0","text":"Tahoe 4.0","name":"Tahoe 4.0"},{"id":"touring","text":"Touring","name":"Touring"},{"id":"track_1_0","text":"Track 1.0","name":"Track 1.0"},{"id":"track_1_0_frameset","text":"Track 1.0 (Frameset)","name":"Track 1.0 (Frameset)"},{"id":"track_2_0","text":"Track 2.0","name":"Track 2.0"}]