{"bike":{"frame_model":"Linden","manufacturer":"Civia","year":2012,"description":"Civia Linden Aluminum","rear_wheel_bsd":622,"stock_photo_url":"https://bikebook.s3.amazonaws.com/uploads/Fr/10406/BK5302-01.jpg","rear_tire_narrow":true},"components":[{"component_type":"fork","description":"Civia Linden Aluminum"},{"component_type":"crankset","description":"FSA Vero compact 50/34"},{"component_type":"cog/cassette/freewheel","description":"Shimano 8 speed 11-32"},{"component_type":"derailleur","description":"Shimano Alivio","front_or_rear":"rear"},{"component_type":"derailleur","description":"Shimano R440","front_or_rear":"front"},{"component_type":"headset","description":"FSA TH-888"},{"component_type":"stem","description":"Civia stem"},{"component_type":"handlebar","description":"Civia Colfax 50 degree"},{"component_type":"seatpost","description":"Civia Seatpost"},{"component_type":"saddle","description":"Velo saddle"},{"component_type":"pedals","description":"Wellgo Alloy platform"},{"component_type":"kickstand","description":"Nuvo single leg"},{"component_type":"shifter","description":"Shimano R441","front_or_rear":"both"},{"component_type":"brake lever","description":"Tektro","front_or_rear":"both"},{"component_type":"brake","description":"Tektro R556 long pull","front_or_rear":"both"},{"component_type":"grips/tape","description":"Civia Ergo Grips brown"},{"component_type":"rack","description":"designed for one","front_or_rear":"front"},{"component_type":"rack","description":"designed for one","front_or_rear":"rear"},{"component_type":"fender","description":"designed for fenders","front_or_rear":"both"},{"component_type":"hub","description":"Shimano HB-RM60","front_or_rear":"front"},{"component_type":"hub","description":"Shimano FH-RM60","front_or_rear":"rear"},{"component_type":"rim","description":"Alex DH19","front_or_rear":"both"},{"component_type":"tire","description":"Continental Tour Ride 700x32","front_or_rear":"both"},{"component_type":"tube","description":"Presta Valve","front_or_rear":"both"},{"component_type":"spokes","description":"Straight gauge"},{"component_type":"nipples","description":"Brass"}]}