{"bike":{"frame_model":"Hotrock 20 6-Speed Boys","manufacturer":"Specialized","year":2004,"description":"Formed top tube, Cr-Mo seat tube, freeride style","paint_description":["Silver","Yellow"],"manufacturers_url":"http://www.specialized.com/us/en/bikes/archive/2004/2004hotrock/04hotrock206-speedboys","stock_photo_url":"https://bikebook.s3.amazonaws.com/uploads/Fr/4693/04Hotrock206BoySil_l.jpg","stock_photo_small":"https://bikebook.s3.amazonaws.com/uploads/Fr/4693/medium_04Hotrock206BoySil_l.jpg"},"components":[{"component_type":"fork","description":"RST 200K, 51mm travel, Hi-Ten steerer and 25.4mm stanchions, coil, cold forged alloy crown, 1-piece alloy lowers","cgroup":"Frame and fork"},{"component_type":"headset","description":"1 1/8\" Threadless, sealed loose ball","cgroup":"Frame and fork"},{"component_type":"stem","description":"A-Head alloy, 15 degree rise, 60mm length","cgroup":"Additional parts"},{"component_type":"handlebar","description":"Steel, 30mm rise,10 degree sweep, 540mm width","cgroup":"Additional parts"},{"component_type":"grips/tape","description":"Specialized Kraton \"Revo\" style","cgroup":"Additional parts"},{"component_type":"brake","description":"Tektro, alloy linear pull, stainless steel pipe, 60mm all weather pads","front_or_rear":"front","cgroup":"Drivetrain and brakes"},{"component_type":"brake","description":"Tektro, alloy linear pull, stainless steel pipe, 60mm all weather pads","front_or_rear":"rear","cgroup":"Drivetrain and brakes"},{"component_type":"brake lever","description":"Tektro junior \"V\", alloy, linear pull compatible","front_or_rear":"both","cgroup":"Drivetrain and brakes"},{"component_type":"derailleur","description":"Shimano Tourney","front_or_rear":"rear","cgroup":"Drivetrain and brakes"},{"component_type":"shifter","description":"Shimano Revo, twist (right only)","front_or_rear":"both","cgroup":"Drivetrain and brakes"},{"component_type":"cog/cassette/freewheel","description":"Shimano HG, 6-speed, 14x28t","cgroup":"Drivetrain and brakes"},{"component_type":"chain","description":"Shimano IG","cgroup":"Drivetrain and brakes"},{"component_type":"crankset","description":"Specialized forged alloy 140mm","cgroup":"Drivetrain and brakes"},{"component_type":"chainrings","description":"36S, outer guard, dual roller chain tensioner","cgroup":"Drivetrain and brakes"},{"component_type":"bottom bracket","description":"Square taper, 68mm shell, 128mm spindle, water sealed loose ball","cgroup":"Drivetrain and brakes"},{"component_type":"pedals","description":"Junior resin platform with reflectors","cgroup":"Drivetrain and brakes"},{"component_type":"rim","description":"Alex, alloy 20x1.5\", single wall w/ground sidewalls","front_or_rear":"both","cgroup":"Wheels"},{"component_type":"hub","description":"Alloy, 36 hole, sealed loose ball, nutted axle","front_or_rear":"front","cgroup":"Wheels"},{"component_type":"hub","description":"Alloy, 36 hole, sealed loose ball, nutted axle","front_or_rear":"rear","cgroup":"Wheels"},{"component_type":"spokes","description":"2.0mm (14g), stainless steel, brass nipples, L189/R189mm front, L187/R186mm rear","cgroup":"Wheels"},{"component_type":"tire","description":"Specialized Roller 20x2.125 blackwall","front_or_rear":"front","cgroup":"Wheels"},{"component_type":"tire","description":"Specialized Roller 20x2.125 blackwall","front_or_rear":"rear","cgroup":"Wheels"},{"component_type":"tube","description":"Specialized schraeder valve","front_or_rear":"both","cgroup":"Wheels"},{"component_type":"saddle","description":"Specialized Expert Jumping","cgroup":"Additional parts"},{"component_type":"seatpost","description":"Alloy, micro adjust, 27.2x300mm","cgroup":"Additional parts"},{"component_type":"seatpost clamp","description":"Integrated, with chromed allen head binder","cgroup":"Additional parts"},{"component_type":"other","description":"Derailleur protector, chain stay protector, reflectors, clear coat, owners manual","cgroup":"Additional parts"}]}