{"bike":{"frame_model":"X600","manufacturer":"Trek","year":2009,"description":"Alpha Black Aluminum w/smooth welds","sizes":["Men's 50, 55, 60, 65cm; Step-through 45, 50, 55cm"],"wheel_size":622},"components":[{"ctype":"wheel","description":"Bontrager Satellite Plus","front_or_rear":"both"},{"ctype":"tire","description":"Bontrager Satellite SL, 700x35c","front_or_rear":"both"},{"ctype":"shifter","description":"Shimano Deore LX, 9 speed","front_or_rear":"both"},{"ctype":"derailleur","description":"Shimano Deore LX","front_or_rear":"front"},{"ctype":"derailleur","description":"Shimano Deore LX","front_or_rear":"rear"},{"ctype":"crankset","description":"Shimano Deore LX 48/36/26"},{"ctype":"cog/cassette/freewheel","description":"SRAM PG950 11-34, 9 speed"},{"ctype":"pedals","description":"Dual density platform w/aluminum body"},{"ctype":"saddle","description":"Selle Royal Lookin Freccia"},{"ctype":"seatpost","description":"Bontrager SSR, carbon"},{"ctype":"handlebars","description":"Bontrager Satellite Elite, carbon"},{"ctype":"stem","description":"Bontrager Race Adjust"},{"ctype":"headset","description":"Threaded semi-integrated w/semi-cartridge bearings, sealed"},{"ctype":"brake","description":"Shimano M432 w/Shimano Deore LX levers","front_or_rear":"both"},{"ctype":"other","description":"Selle Royal saddle bag, Axa RLS Plus cable lock"}]}