{"bike":{"frame_model":"PeriScope Trident","manufacturer":"Co-Motion","year":2014,"description":"Handbuilt frame with zonally-butted cro-moly steel tubing, FSA Omega captain bar & stem; Co-Motion Stoker bar & stem","original_msrp":"$6495.00","cycle_type":"Tandem","stock_photo_url":"https://bikebook.s3.amazonaws.com/uploads/Fr/3044/trident12.jpg"},"components":[{"component_type":"fork","description":"Co-Motion Taper Gauge w/ CNC Tandem Steerer"},{"component_type":"headset","description":"FSA Orbit"},{"component_type":"shifter","description":"Shimano Ultegra 6703 Triple","front_or_rear":"both"},{"component_type":"brake","description":"TRP Spyre w/ 203mm Rotor","front_or_rear":"both"},{"component_type":"drivetrain","description":"FSA Gossamer Tandem cranks; 11-32t 10spd cassette"},{"component_type":"saddle","description":"Co-Motion 29.8"},{"component_type":"seatpost","description":"Selle Italia X1 & X1 Lady"},{"component_type":"wheel","description":"Velocity Dyad/Aeroheat Rims; DT Swiss DT540 Tandem Hubs","front_or_rear":"both"},{"component_type":"tire","description":"Schwalbe Spicer 26x1.5\"","front_or_rear":"both"}]}