{"bike":{"frame_model":"Jack 3","manufacturer":"Trek","year":2007,"description":"Alpha Aluminum","original_paints":["Gloss White"],"sizes":["13, 15, 17\""],"stock_image":"https://bikebook.s3.amazonaws.com/uploads/Fr/2160/jack3_white.jpg"},"components":[{"ctype":"wheel","description":"Shimano M475 disc hubs; Sun Rhyno Lite rims","front_or_rear":"both"},{"ctype":"tire","description":"Bontrager Earl, 26x2.4\", 27 tpi","front_or_rear":"both"},{"ctype":"shifter","description":"Shimano Deore, 9 speed","front_or_rear":"both"},{"ctype":"derailleur","description":"Shimano Deore","front_or_rear":"front"},{"ctype":"derailleur","description":"Shimano Deore LX","front_or_rear":"rear"},{"ctype":"crankset","description":"Bontrager King Earl 36/24 w/bash guard"},{"ctype":"cog/cassette/freewheel","description":"SRAM PG950 11-34, 9 speed"},{"ctype":"pedals","description":"Bontrager Big Earl platform"},{"ctype":"saddle","description":"Bontrager Big Earl"},{"ctype":"seatpost","description":"Bontrager King Earl"},{"ctype":"handlebars","description":"Bontrager Big Earl, 70mm rise, 31.8mm"},{"ctype":"stem","description":"Bontrager Earl, 10 degree, 31.8mm"},{"ctype":"headset","description":"Aheadset w/semi-cartridge bearings, Cro-Moly"},{"ctype":"brake","description":"Avid Juicy 5, hydraulic disc, 8\" front, 6\" rear","front_or_rear":"both"}]}