{"bike":{"frame_model":"Skye S","manufacturer":"Trek","year":2013,"description":"WSD Alpha Silver Aluminum w/semi-integrated head tube, rack & fender mounts, disc compatible dropouts, replaceable derailleur hanger","paint_description":"Satin Trek Black","rear_wheel_bsd":559,"stock_photo_url":"https://bikebook.s3.amazonaws.com/uploads/Fr/405/57857"},"components":[{"component_type":"wheel","description":"Formula FM21 alloy front hub; Shimano RM30 alloy rear hub w/Bontrager AT-550 36-hole rims","front_or_rear":"both"},{"component_type":"tire","description":"Bontrager LT3, 26x2.0\"","front_or_rear":"both"},{"component_type":"shifter","description":"Shimano Altus, 8 speed","front_or_rear":"both"},{"component_type":"derailleur","description":"Shimano Altus","front_or_rear":"front"},{"component_type":"derailleur","description":"Shimano Acera","front_or_rear":"rear"},{"component_type":"crankset","description":"Shimano M171, 42/34/24"},{"component_type":"cog/cassette/freewheel","description":"Shimano HG20 12-32, 8 speed"},{"component_type":"pedals","description":"Wellgo nylon platform"},{"component_type":"saddle","description":"Bontrager SSR WSD"},{"component_type":"seatpost","description":"Bontrager SSR, 31.6mm, 20mm offset"},{"component_type":"handlebar","description":"Bontrager Riser, 25.4mm, 30mm rise"},{"component_type":"stem","description":"Bontrager Approved, 25.4mm, 40 degree"},{"component_type":"headset","description":"1-1/8\" threadless"},{"component_type":"brake","description":"Tektro alloy linear-pull brakes w/Shimano Altus levers","front_or_rear":"both"},{"component_type":"other","description":"Fender and rack mounts"}]}