{"bike":{"frame_model":"Wahoo Disc","manufacturer":"Gary Fisher","year":2006,"description":"Gold Series 6061 T6 internally and externally butted aluminum | Genesis Geometry","original_paints":["Metallic Black"],"sizes":["XS (13\"), SM (15.5\"), MD (17.5\"), LG (19\"), XL (21\")"],"stock_image":"https://bikebook.s3.amazonaws.com/uploads/Fr/2522/wahoo_disc.jpg"},"components":[{"ctype":"fork","description":"RockShox J1 | 100mm travel | Preload adjust"},{"ctype":"tire","description":"Bontrager Jones XR 26x2.25 / Bontrager Jones XR 26x2.2","front_or_rear":"both"},{"ctype":"shifter","description":"Shimano EF50","front_or_rear":"both"},{"ctype":"derailleur","description":"Shimano Acera","front_or_rear":"front"},{"ctype":"derailleur","description":"Shimano Alivio","front_or_rear":"rear"},{"ctype":"crankset","description":"Shimano MC09 42/32/22"},{"ctype":"cog/cassette/freewheel","description":"SRAM PG830 | 11-32 | 8spd"},{"ctype":"pedals","description":"Nylon platform"},{"ctype":"saddle","description":"Bontrager Select ATB"},{"ctype":"seatpost","description":"Bontrager Sport"},{"ctype":"handlebars","description":"Bontrager Crowbar Sport"},{"ctype":"stem","description":"Bontrager Sport | 10d rise"},{"ctype":"headset","description":"Aheadset | semi-cartridge | sealed"},{"ctype":"brake","description":"Hayes MX-2 mechanical disc | 6\" rotor w/ Shimano EF50","front_or_rear":"both"}]}