{"bike":{"frame_model":"Super Pista Frameset","manufacturer":"Bianchi","year":2013,"description":"Frame: D2 Pista Alloy.","paint_description":["Matte Black, Celeste"],"manufacturers_url":"http://www.bianchiusa.com/archives/2013/fixed-gear/super-pista-frameset/#","stock_photo_url":"https://bikebook.s3.amazonaws.com/uploads/Fr/13189/Super-Pista.jpg","stock_photo_small":"https://bikebook.s3.amazonaws.com/uploads/Fr/13189/medium_Super-Pista.jpg"},"components":[{"component_type":"fork","description":"Bianchi Carbon Straight Aero Blade Alu/Carbon 1 1/8\"","cgroup":"Frame and fork"},{"component_type":"headset","description":"FSA Orbit CE Plus","cgroup":"Frame and fork"}]}