{"bike":{"frame_model":"Tricross Elite Disc Apex Compact","manufacturer":"Specialized","year":2012,"description":"Specialized A1 Premium Aluminum, smooth weld, fully manipulated tubing, semi-compact design, integrated headset, internal cable routing, rack and fender fittings, disc only","paint_description":"Natural Aluminum","stock_photo_url":"https://bikebook.s3.amazonaws.com/uploads/Fr/4173/9679"},"components":[{"ctype":"fork","description":"Full alloy, low-rider rack/fender fittings, disc only"},{"ctype":"headset","description":"1-1/8\" sealed Cr-Mo cartridge bearings integrated w/ headset, 20mm alloy cone spacer, w/ 20mm of spacers"},{"ctype":"stem","description":"Specialized EliteSet, 3D forged alloy, 12-degree, 4-position adjustable, 4-bolt, 31.8mm clamp"},{"ctype":"handlebar","description":"Specialized H2 Ergo Comp, alloy"},{"ctype":"grips/tape","description":"Specialized TriCross wrap w/ 2.5 gel pads"},{"ctype":"brake","description":"Avid BB5 disc, 160mm","front_or_rear":"front"},{"ctype":"brake","description":"Avid BB5 disc, 140mm","front_or_rear":"rear"},{"ctype":"brake lever","description":"New TriCross Comp secondary brake levers","front_or_rear":"both"},{"ctype":"derailleur","description":"SRAM Apex","front_or_rear":"front"},{"ctype":"derailleur","description":"SRAM Apex, mid cage","front_or_rear":"rear"},{"ctype":"shifter","description":"SRAM Apex DoubleTap, 10-speed","front_or_rear":"both"},{"ctype":"cog/cassette/freewheel","description":"SRAM Apex, 10-speed, 11-32t"},{"ctype":"chain","description":"KMC X10 CP"},{"ctype":"crankset","description":"FSA Gossamer"},{"ctype":"chainrings","description":"50/34"},{"ctype":"bottom bracket","description":"With crankset"},{"ctype":"pedals","description":"Nylon flat test ride, loose ball, w/ reflectors"},{"ctype":"rim","description":"Alex Handsome Dragon 2.0, 32 hole","front_or_rear":"both"},{"ctype":"hub","description":"Forged alloy hub, 32h","front_or_rear":"front"},{"ctype":"hub","description":"Forged aluminum, double sealed ball bearings, cassette, QR, 32h","front_or_rear":"rear"},{"ctype":"spokes","description":"Stainless 14g"},{"ctype":"tire","description":"Specialized Borough CX Armadillo Elite, 120 TPI, aramid bead, 700x32c","front_or_rear":"front"},{"ctype":"tire","description":"Specialized Borough CX Armadillo Elite, 120 TPI, aramid bead, 700x32c","front_or_rear":"rear"},{"ctype":"tube","description":"Lightweight, presta","front_or_rear":"both"},{"ctype":"saddle","description":"Body Geometry Riva Plus TriCross, 155mm"},{"ctype":"seatpost","description":"New Specialized Sport, alloy, 27.2mm"},{"ctype":"seatpost clamp","description":"Alloy, 31.8mm"},{"ctype":"other","description":"chainstay protector, chain catcher, derailleur hanger, clear coat, owner's manual"}]}