{"bike":{"frame_model":"X-Caliber","manufacturer":"Gary Fisher","year":2008,"description":"Platinum Series 6066 butted and hydroformed aluminum, G2 29\" Geometry","paint_description":"Ceramic White","stock_photo_url":"https://bikebook.s3.amazonaws.com/uploads/Fr/2068/xcal.jpg"},"components":[{"component_type":"fork","description":"Fox F80 RL 29 w/air pressure, rebound, lockout, alloy steerer, 80mm travel, G2 offset"},{"component_type":"wheel","description":"Bontrager Rhythm 29 disc(tubeless ready rim strips, valves and sealant sold separately)","front_or_rear":"both"},{"component_type":"tire","description":"Bontrager Jones ACX, 29x2.2, folding, tubeless ready","front_or_rear":"both"},{"component_type":"shifter","description":"SRAM X.7","front_or_rear":"both"},{"component_type":"derailleur","description":"Shimano Deore","front_or_rear":"front"},{"component_type":"derailleur","description":"SRAM X.7","front_or_rear":"rear"},{"component_type":"crankset","description":"Shimano M521 44/32/22, Octalink"},{"component_type":"cog/cassette/freewheel","description":"SRAM PG950 11-34, 9 speed"},{"component_type":"saddle","description":"Bontrager Race"},{"component_type":"seatpost","description":"Bontrager Sport"},{"component_type":"handlebar","description":"Bontrager Select Big Sweep, 31.8mm, 12d"},{"component_type":"stem","description":"Bontrager Select, 31.8mm, 7 degree"},{"component_type":"headset","description":"Aheadset semi-integrated w/semi-cartridge bearings, sealed"},{"component_type":"brake","description":"Shimano M485, hydraulic disc, 160mm rotors","front_or_rear":"both"}]}