{"bike":{"frame_model":"4300 WSD","manufacturer":"Trek","year":2006,"description":"Alpha SL Aluminum","paint_description":"Platinum Silver","stock_photo_url":"https://bikebook.s3.amazonaws.com/uploads/Fr/2323/4300wsd_platinumsilver.jpg"},"components":[{"ctype":"wheel","description":"Alloy front, Shimano RM60 rear hub; Bontrager Camino rims","front_or_rear":"both"},{"ctype":"tire","description":"Bontrager Connection Trail, 26x2.0\"","front_or_rear":"both"},{"ctype":"shifter","description":"Shimano EF50","front_or_rear":"both"},{"ctype":"derailleur","description":"Shimano C050","front_or_rear":"front"},{"ctype":"derailleur","description":"Shimano Alivio","front_or_rear":"rear"},{"ctype":"crankset","description":"SR XCC-150 42/34/24"},{"ctype":"cog/cassette/freewheel","description":"SRAM PG830 11-32, 8 speed"},{"ctype":"pedals","description":"Alloy platform"},{"ctype":"saddle","description":"Bontrager Select FIT Basic"},{"ctype":"seatpost","description":"Bontrager Sport"},{"ctype":"handlebar","description":"Bontrager Crowbar Sport, 25mm rise"},{"ctype":"stem","description":"Bontrager Sport, 25 degree"},{"ctype":"headset","description":"Aheadset Slimstak w/semi-cartridge bearings, sealed"},{"ctype":"brake","description":"Tektro V w/Shimano EF50 levers","front_or_rear":"both"},{"ctype":"other","description":"Bontrager Select FIT grips"}]}