{"2012":[{"id":"aguila","text":"AGUILA\u003Cspan class='f_msrp'\u003E$769.00\u003C/span\u003E","name":"AGUILA"},{"id":"alite","text":"ALITE\u003Cspan class='f_msrp'\u003E$1,699.00\u003C/span\u003E","name":"ALITE"},{"id":"alite_100","text":"ALITE 100\u003Cspan class='f_msrp'\u003E$359.00\u003C/span\u003E","name":"ALITE 100"},{"id":"alite_1000","text":"ALITE 1000\u003Cspan class='f_msrp'\u003E$869.00\u003C/span\u003E","name":"ALITE 1000"},{"id":"alite_150","text":"ALITE 150\u003Cspan class='f_msrp'\u003E$439.00\u003C/span\u003E","name":"ALITE 150"},{"id":"alite_150_ladies","text":"ALITE 150 (Ladies)\u003Cspan class='f_msrp'\u003E$439.00\u003C/span\u003E","name":"ALITE 150 (Ladies)"},{"id":"alite_2000","text":"ALITE 2000\u003Cspan class='f_msrp'\u003E$1,199.00\u003C/span\u003E","name":"ALITE 2000"},{"id":"alite_2000_ladies","text":"ALITE 2000 (Ladies)\u003Cspan class='f_msrp'\u003E$1,199.00\u003C/span\u003E","name":"ALITE 2000 (Ladies)"},{"id":"alite_24","text":"ALITE 24\u003Cspan class='f_msrp'\u003E$509.00\u003C/span\u003E","name":"ALITE 24"},{"id":"alite_300","text":"ALITE 300\u003Cspan class='f_msrp'\u003E$489.00\u003C/span\u003E","name":"ALITE 300"},{"id":"alite_300_ladies","text":"ALITE 300 (Ladies)\u003Cspan class='f_msrp'\u003E$489.00\u003C/span\u003E","name":"ALITE 300 (Ladies)"},{"id":"alite_350","text":"ALITE 350\u003Cspan class='f_msrp'\u003E$549.00\u003C/span\u003E","name":"ALITE 350"},{"id":"alite_350_ladies","text":"ALITE 350 (Ladies)\u003Cspan class='f_msrp'\u003E$549.00\u003C/span\u003E","name":"ALITE 350 (Ladies)"},{"id":"alite_40","text":"ALITE 40\u003Cspan class='f_msrp'\u003E$269.00\u003C/span\u003E","name":"ALITE 40"},{"id":"alite_40_ladies","text":"ALITE 40 (Ladies)\u003Cspan class='f_msrp'\u003E$269.00\u003C/span\u003E","name":"ALITE 40 (Ladies)"},{"id":"alite_500","text":"ALITE 500\u003Cspan class='f_msrp'\u003E$709.00\u003C/span\u003E","name":"ALITE 500"},{"id":"alite_500_ladies","text":"ALITE 500 (Ladies)\u003Cspan class='f_msrp'\u003E$709.00\u003C/span\u003E","name":"ALITE 500 (Ladies)"},{"id":"bajada","text":"BAJADA\u003Cspan class='f_msrp'\u003E$1,899.00\u003C/span\u003E","name":"BAJADA"},{"id":"brentwood","text":"BRENTWOOD\u003Cspan class='f_msrp'\u003E$359.00\u003C/span\u003E","name":"BRENTWOOD"},{"id":"brentwood_ladies","text":"BRENTWOOD (Ladies)\u003Cspan class='f_msrp'\u003E$359.00\u003C/span\u003E","name":"BRENTWOOD (Ladies)"},{"id":"cidi_3","text":"CIDI-3\u003Cspan class='f_msrp'\u003E$479.00\u003C/span\u003E","name":"CIDI-3"},{"id":"cidi_3_ladies","text":"CIDI-3 (Ladies)\u003Cspan class='f_msrp'\u003E$479.00\u003C/span\u003E","name":"CIDI-3 (Ladies)"},{"id":"cidi_8","text":"CIDI-8\u003Cspan class='f_msrp'\u003E$679.00\u003C/span\u003E","name":"CIDI-8"},{"id":"cidi_8_ladies","text":"CIDI-8 (Ladies)\u003Cspan class='f_msrp'\u003E$679.00\u003C/span\u003E","name":"CIDI-8 (Ladies)"},{"id":"cross","text":"CROSS\u003Cspan class='f_msrp'\u003E$1,699.00\u003C/span\u003E","name":"CROSS"},{"id":"cx_100","text":"CX 100\u003Cspan class='f_msrp'\u003E$909.00\u003C/span\u003E","name":"CX 100"},{"id":"cx_300","text":"CX 300\u003Cspan class='f_msrp'\u003E$1,799.00\u003C/span\u003E","name":"CX 300"},{"id":"dh150_dh_pro","text":"DH150 DH Pro\u003Cspan class='f_msrp'\u003E$4,299.00\u003C/span\u003E","name":"DH150 DH Pro"},{"id":"dh300_dh_team","text":"DH300 DH Team\u003Cspan class='f_msrp'\u003E$5,799.00\u003C/span\u003E","name":"DH300 DH Team"},{"id":"dj_150","text":"DJ 150\u003Cspan class='f_msrp'\u003E$949.00\u003C/span\u003E","name":"DJ 150"},{"id":"dj_24","text":"DJ 24\u003Cspan class='f_msrp'\u003E$579.00\u003C/span\u003E","name":"DJ 24"},{"id":"dj_50","text":"DJ 50\u003Cspan class='f_msrp'\u003E$679.00\u003C/span\u003E","name":"DJ 50"},{"id":"flagstaff","text":"FLAGSTAFF\u003Cspan class='f_msrp'\u003E$2,699.00\u003C/span\u003E","name":"FLAGSTAFF"},{"id":"flite_100","text":"FLITE 100\u003Cspan class='f_msrp'\u003E$659.00\u003C/span\u003E","name":"FLITE 100"},{"id":"flite_150","text":"FLITE 150\u003Cspan class='f_msrp'\u003E$509.00\u003C/span\u003E","name":"FLITE 150"},{"id":"flite_150_ladies","text":"FLITE 150 (Ladies)\u003Cspan class='f_msrp'\u003E$509.00\u003C/span\u003E","name":"FLITE 150 (Ladies)"},{"id":"flite_220","text":"FLITE 220\u003Cspan class='f_msrp'\u003E$599.00\u003C/span\u003E","name":"FLITE 220"},{"id":"flite_223","text":"FLITE 223\u003Cspan class='f_msrp'\u003E$599.00\u003C/span\u003E","name":"FLITE 223"},{"id":"flite_223_ladies","text":"FLITE 223 (Ladies)\u003Cspan class='f_msrp'\u003E$599.00\u003C/span\u003E","name":"FLITE 223 (Ladies)"},{"id":"flite_300","text":"FLITE 300\u003Cspan class='f_msrp'\u003E$769.00\u003C/span\u003E","name":"FLITE 300"},{"id":"flite_450","text":"FLITE 450\u003Cspan class='f_msrp'\u003E$979.00\u003C/span\u003E","name":"FLITE 450"},{"id":"flite_500","text":"FLITE 500\u003Cspan class='f_msrp'\u003E$1,239.00\u003C/span\u003E","name":"FLITE 500"},{"id":"flite_720","text":"FLITE 720\u003Cspan class='f_msrp'\u003E$1,599.00\u003C/span\u003E","name":"FLITE 720"},{"id":"flite_720_ladies","text":"FLITE 720 (Ladies)\u003Cspan class='f_msrp'\u003E$1,599.00\u003C/span\u003E","name":"FLITE 720 (Ladies)"},{"id":"flite_747","text":"FLITE 747\u003Cspan class='f_msrp'\u003E$1,699.00\u003C/span\u003E","name":"FLITE 747"},{"id":"flite_750","text":"FLITE 750\u003Cspan class='f_msrp'\u003E$1,799.00\u003C/span\u003E","name":"FLITE 750"},{"id":"flite_780","text":"FLITE 780\u003Cspan class='f_msrp'\u003E$3,799.00\u003C/span\u003E","name":"FLITE 780"},{"id":"flite_850","text":"FLITE 850\u003Cspan class='f_msrp'\u003E$2,399.00\u003C/span\u003E","name":"FLITE 850"},{"id":"flite_900","text":"FLITE 900\u003Cspan class='f_msrp'\u003E$2,999.00\u003C/span\u003E","name":"FLITE 900"},{"id":"flite_950","text":"FLITE 950\u003Cspan class='f_msrp'\u003E$5,099.00\u003C/span\u003E","name":"FLITE 950"},{"id":"flite_team","text":"FLITE TEAM\u003Cspan class='f_msrp'\u003E$5,299.00\u003C/span\u003E","name":"FLITE TEAM"},{"id":"green","text":"GREEN\u003Cspan class='f_msrp'\u003E$359.00\u003C/span\u003E","name":"GREEN"},{"id":"green_ladies","text":"GREEN (Ladies)\u003Cspan class='f_msrp'\u003E$359.00\u003C/span\u003E","name":"GREEN (Ladies)"},{"id":"hot_rod","text":"HOT ROD\u003Cspan class='f_msrp'\u003E$259.00\u003C/span\u003E","name":"HOT ROD"},{"id":"iped","text":"IPED\u003Cspan class='f_msrp'\u003E$389.00\u003C/span\u003E","name":"IPED"},{"id":"iped_3_speed","text":"IPED 3-SPEED\u003Cspan class='f_msrp'\u003E$439.00\u003C/span\u003E","name":"IPED 3-SPEED"},{"id":"k9_police","text":"K9 POLICE\u003Cspan class='f_msrp'\u003E$979.00\u003C/span\u003E","name":"K9 POLICE"},{"id":"latte","text":"LATTE\u003Cspan class='f_msrp'\u003E$329.00\u003C/span\u003E","name":"LATTE"},{"id":"lucky_7","text":"LUCKY 7\u003Cspan class='f_msrp'\u003E$2,899.00\u003C/span\u003E","name":"LUCKY 7"},{"id":"milano","text":"MILANO\u003Cspan class='f_msrp'\u003E$1,899.00\u003C/span\u003E","name":"MILANO"},{"id":"mocha","text":"MOCHA\u003Cspan class='f_msrp'\u003E$399.00\u003C/span\u003E","name":"MOCHA"},{"id":"prescott","text":"PRESCOTT\u003Cspan class='f_msrp'\u003E$3,699.00\u003C/span\u003E","name":"PRESCOTT"},{"id":"raptor","text":"RAPTOR\u003Cspan class='f_msrp'\u003E$299.00\u003C/span\u003E","name":"RAPTOR"},{"id":"saguaro","text":"SAGUARO\u003Cspan class='f_msrp'\u003E$2,899.00\u003C/span\u003E","name":"SAGUARO"},{"id":"sixfifty_603","text":"SIXFIFTY 603\u003Cspan class='f_msrp'\u003E$769.00\u003C/span\u003E","name":"SIXFIFTY 603"},{"id":"sixfifty_606","text":"SIXFIFTY 606\u003Cspan class='f_msrp'\u003E$1,399.00\u003C/span\u003E","name":"SIXFIFTY 606"},{"id":"sixfifty_608","text":"SIXFIFTY 608\u003Cspan class='f_msrp'\u003E$3,299.00\u003C/span\u003E","name":"SIXFIFTY 608"},{"id":"sixfifty_609","text":"SIXFIFTY 609\u003Cspan class='f_msrp'\u003E$4,299.00\u003C/span\u003E","name":"SIXFIFTY 609"},{"id":"sixfifty_656xc","text":"SIXFIFTY 656XC\u003Cspan class='f_msrp'\u003E$2,599.00\u003C/span\u003E","name":"SIXFIFTY 656XC"},{"id":"sj_100","text":"SJ 100\u003Cspan class='f_msrp'\u003E$619.00\u003C/span\u003E","name":"SJ 100"},{"id":"sj_200","text":"SJ 200\u003Cspan class='f_msrp'\u003E$819.00\u003C/span\u003E","name":"SJ 200"},{"id":"sj_300","text":"SJ 300\u003Cspan class='f_msrp'\u003E$979.00\u003C/span\u003E","name":"SJ 300"},{"id":"smoothie","text":"SMOOTHIE\u003Cspan class='f_msrp'\u003E$439.00\u003C/span\u003E","name":"SMOOTHIE"},{"id":"smoothie_3_speed","text":"SMOOTHIE 3-SPEED\u003Cspan class='f_msrp'\u003E$499.00\u003C/span\u003E","name":"SMOOTHIE 3-SPEED"},{"id":"smoothie_3_speed_ladies","text":"SMOOTHIE 3-SPEED (Ladies)\u003Cspan class='f_msrp'\u003E$499.00\u003C/span\u003E","name":"SMOOTHIE 3-SPEED (Ladies)"},{"id":"smoothie_ladies","text":"SMOOTHIE (Ladies)\u003Cspan class='f_msrp'\u003E$439.00\u003C/span\u003E","name":"SMOOTHIE (Ladies)"},{"id":"sport","text":"SPORT\u003Cspan class='f_msrp'\u003E$1,059.00\u003C/span\u003E","name":"SPORT"},{"id":"syntaur","text":"SYNTAUR\u003Cspan class='f_msrp'\u003E$329.00\u003C/span\u003E","name":"SYNTAUR"},{"id":"t_rex","text":"T-REX\u003Cspan class='f_msrp'\u003E$329.00\u003C/span\u003E","name":"T-REX"},{"id":"tc_100","text":"TC 100\u003Cspan class='f_msrp'\u003E$359.00\u003C/span\u003E","name":"TC 100"},{"id":"tc_100_ladies","text":"TC 100 (Ladies)\u003Cspan class='f_msrp'\u003E$359.00\u003C/span\u003E","name":"TC 100 (Ladies)"},{"id":"tc_150","text":"TC 150\u003Cspan class='f_msrp'\u003E$459.00\u003C/span\u003E","name":"TC 150"},{"id":"tc_150_ladies","text":"TC 150 (Ladies)\u003Cspan class='f_msrp'\u003E$459.00\u003C/span\u003E","name":"TC 150 (Ladies)"},{"id":"team_29","text":"TEAM 29\u003Cspan class='f_msrp'\u003E$4,299.00\u003C/span\u003E","name":"TEAM 29"},{"id":"tempe","text":"TEMPE\u003Cspan class='f_msrp'\u003E$1,029.00\u003C/span\u003E","name":"TEMPE"},{"id":"tr_101","text":"TR 101\u003Cspan class='f_msrp'\u003E$1,099.00\u003C/span\u003E","name":"TR 101"},{"id":"tricycle_3_speed","text":"TRICYCLE 3-SPEED\u003Cspan class='f_msrp'\u003E$709.00\u003C/span\u003E","name":"TRICYCLE 3-SPEED"},{"id":"tricycle_single_speed","text":"TRICYCLE SINGLE SPEED\u003Cspan class='f_msrp'\u003E$599.00\u003C/span\u003E","name":"TRICYCLE SINGLE SPEED"},{"id":"tucson","text":"TUCSON\u003Cspan class='f_msrp'\u003E$1,299.00\u003C/span\u003E","name":"TUCSON"},{"id":"urban_soul","text":"URBAN SOUL\u003Cspan class='f_msrp'\u003E$399.00\u003C/span\u003E","name":"URBAN SOUL"},{"id":"urban_x","text":"URBAN X\u003Cspan class='f_msrp'\u003E$569.00\u003C/span\u003E","name":"URBAN X"},{"id":"urban_xcape","text":"URBAN XCAPE\u003Cspan class='f_msrp'\u003E$419.00\u003C/span\u003E","name":"URBAN XCAPE"},{"id":"urban_xcape_ladies","text":"URBAN XCAPE (Ladies)\u003Cspan class='f_msrp'\u003E$419.00\u003C/span\u003E","name":"URBAN XCAPE (Ladies)"},{"id":"urban_xcel","text":"URBAN XCEL\u003Cspan class='f_msrp'\u003E$769.00\u003C/span\u003E","name":"URBAN XCEL"},{"id":"urban_xpress","text":"URBAN XPRESS\u003Cspan class='f_msrp'\u003E$569.00\u003C/span\u003E","name":"URBAN XPRESS"},{"id":"urban_xpress_ladies","text":"URBAN XPRESS (Ladies)\u003Cspan class='f_msrp'\u003E$569.00\u003C/span\u003E","name":"URBAN XPRESS (Ladies)"},{"id":"vitamin_a","text":"VITAMIN A\u003Cspan class='f_msrp'\u003E$439.00\u003C/span\u003E","name":"VITAMIN A"},{"id":"vitamin_a_ladies","text":"VITAMIN A (Ladies)\u003Cspan class='f_msrp'\u003E$439.00\u003C/span\u003E","name":"VITAMIN A (Ladies)"},{"id":"vitamin_b","text":"VITAMIN B\u003Cspan class='f_msrp'\u003E$629.00\u003C/span\u003E","name":"VITAMIN B"},{"id":"vitamin_b_ladies","text":"VITAMIN B (Ladies)\u003Cspan class='f_msrp'\u003E$629.00\u003C/span\u003E","name":"VITAMIN B (Ladies)"},{"id":"vitamin_c","text":"VITAMIN C\u003Cspan class='f_msrp'\u003E$709.00\u003C/span\u003E","name":"VITAMIN C"},{"id":"westwood","text":"WESTWOOD\u003Cspan class='f_msrp'\u003E$459.00\u003C/span\u003E","name":"WESTWOOD"},{"id":"westwood_ladies","text":"WESTWOOD (Ladies)\u003Cspan class='f_msrp'\u003E$459.00\u003C/span\u003E","name":"WESTWOOD (Ladies)"},{"id":"winslow","text":"WINSLOW\u003Cspan class='f_msrp'\u003E$639.00\u003C/span\u003E","name":"WINSLOW"},{"id":"xc_104","text":"XC 104\u003Cspan class='f_msrp'\u003E$1,249.00\u003C/span\u003E","name":"XC 104"},{"id":"xc_204","text":"XC 204\u003Cspan class='f_msrp'\u003E$1,599.00\u003C/span\u003E","name":"XC 204"},{"id":"xc_204_ladies","text":"XC 204 (Ladies)\u003Cspan class='f_msrp'\u003E$1,599.00\u003C/span\u003E","name":"XC 204 (Ladies)"},{"id":"xc_604","text":"XC 604\u003Cspan class='f_msrp'\u003E$1,999.00\u003C/span\u003E","name":"XC 604"},{"id":"xc_704","text":"XC 704\u003Cspan class='f_msrp'\u003E$3,499.00\u003C/span\u003E","name":"XC 704"},{"id":"xc_team","text":"XC TEAM\u003Cspan class='f_msrp'\u003E$5,299.00\u003C/span\u003E","name":"XC TEAM"},{"id":"xct_536","text":"XCT 536\u003Cspan class='f_msrp'\u003E$2,199.00\u003C/span\u003E","name":"XCT 536"},{"id":"xct_556","text":"XCT 556\u003Cspan class='f_msrp'\u003E$2,899.00\u003C/span\u003E","name":"XCT 556"},{"id":"yuma","text":"YUMA\u003Cspan class='f_msrp'\u003E$1,799.00\u003C/span\u003E","name":"YUMA"}],"2013":[{"id":"aguila","text":"AGUILA\u003Cspan class='f_msrp'\u003E$799.00\u003C/span\u003E","name":"AGUILA"},{"id":"alite","text":"ALITE\u003Cspan class='f_msrp'\u003E$1,799.00\u003C/span\u003E","name":"ALITE"},{"id":"alite_100","text":"ALITE 100\u003Cspan class='f_msrp'\u003E$449.00\u003C/span\u003E","name":"ALITE 100"},{"id":"alite_1000","text":"ALITE 1000\u003Cspan class='f_msrp'\u003E$979.00\u003C/span\u003E","name":"ALITE 1000"},{"id":"alite_150","text":"ALITE 150\u003Cspan class='f_msrp'\u003E$549.00\u003C/span\u003E","name":"ALITE 150"},{"id":"alite_150_ladies","text":"ALITE 150 (Ladies)\u003Cspan class='f_msrp'\u003E$549.00\u003C/span\u003E","name":"ALITE 150 (Ladies)"},{"id":"alite_2000","text":"ALITE 2000\u003Cspan class='f_msrp'\u003E$1,269.00\u003C/span\u003E","name":"ALITE 2000"},{"id":"alite_2000_ladies","text":"ALITE 2000 (Ladies)\u003Cspan class='f_msrp'\u003E$1,269.00\u003C/span\u003E","name":"ALITE 2000 (Ladies)"},{"id":"alite_24","text":"ALITE 24\u003Cspan class='f_msrp'\u003E$549.00\u003C/span\u003E","name":"ALITE 24"},{"id":"alite_350","text":"ALITE 350\u003Cspan class='f_msrp'\u003E$599.00\u003C/span\u003E","name":"ALITE 350"},{"id":"alite_350_ladies","text":"ALITE 350 (Ladies)\u003Cspan class='f_msrp'\u003E$599.00\u003C/span\u003E","name":"ALITE 350 (Ladies)"},{"id":"alite_40","text":"ALITE 40\u003Cspan class='f_msrp'\u003E$309.00\u003C/span\u003E","name":"ALITE 40"},{"id":"alite_40_ladies","text":"ALITE 40 (Ladies)\u003Cspan class='f_msrp'\u003E$309.00\u003C/span\u003E","name":"ALITE 40 (Ladies)"},{"id":"alite_500","text":"ALITE 500\u003Cspan class='f_msrp'\u003E$769.00\u003C/span\u003E","name":"ALITE 500"},{"id":"alite_500_ladies","text":"ALITE 500 (Ladies)\u003Cspan class='f_msrp'\u003E$769.00\u003C/span\u003E","name":"ALITE 500 (Ladies)"},{"id":"bajada","text":"BAJADA\u003Cspan class='f_msrp'\u003E$1,899.00\u003C/span\u003E","name":"BAJADA"},{"id":"brentwood","text":"BRENTWOOD\u003Cspan class='f_msrp'\u003E$389.00\u003C/span\u003E","name":"BRENTWOOD"},{"id":"brentwood_ladies","text":"BRENTWOOD (Ladies)\u003Cspan class='f_msrp'\u003E$389.00\u003C/span\u003E","name":"BRENTWOOD (Ladies)"},{"id":"cross","text":"CROSS\u003Cspan class='f_msrp'\u003E$1,799.00\u003C/span\u003E","name":"CROSS"},{"id":"cx_300","text":"CX 300\u003Cspan class='f_msrp'\u003E$1,839.00\u003C/span\u003E","name":"CX 300"},{"id":"dh150_dh_pro","text":"DH150 DH Pro\u003Cspan class='f_msrp'\u003E$4,299.00\u003C/span\u003E","name":"DH150 DH Pro"},{"id":"dh300_dh_team","text":"DH300 DH Team\u003Cspan class='f_msrp'\u003E$6,299.00\u003C/span\u003E","name":"DH300 DH Team"},{"id":"dj_24","text":"DJ 24\u003Cspan class='f_msrp'\u003E$599.00\u003C/span\u003E","name":"DJ 24"},{"id":"dj_50","text":"DJ 50\u003Cspan class='f_msrp'\u003E$699.00\u003C/span\u003E","name":"DJ 50"},{"id":"flagstaff","text":"FLAGSTAFF\u003Cspan class='f_msrp'\u003E$2,699.00\u003C/span\u003E","name":"FLAGSTAFF"},{"id":"flite_100","text":"FLITE 100\u003Cspan class='f_msrp'\u003E$669.00\u003C/span\u003E","name":"FLITE 100"},{"id":"flite_150","text":"FLITE 150\u003Cspan class='f_msrp'\u003E$549.00\u003C/span\u003E","name":"FLITE 150"},{"id":"flite_150_ladies","text":"FLITE 150 (Ladies)\u003Cspan class='f_msrp'\u003E$549.00\u003C/span\u003E","name":"FLITE 150 (Ladies)"},{"id":"flite_223","text":"FLITE 223\u003Cspan class='f_msrp'\u003E$669.00\u003C/span\u003E","name":"FLITE 223"},{"id":"flite_223_ladies","text":"FLITE 223 (Ladies)\u003Cspan class='f_msrp'\u003E$669.00\u003C/span\u003E","name":"FLITE 223 (Ladies)"},{"id":"flite_300","text":"FLITE 300\u003Cspan class='f_msrp'\u003E$789.00\u003C/span\u003E","name":"FLITE 300"},{"id":"flite_300_ladies","text":"FLITE 300 (Ladies)\u003Cspan class='f_msrp'\u003E$789.00\u003C/span\u003E","name":"FLITE 300 (Ladies)"},{"id":"flite_350","text":"FLITE 350\u003Cspan class='f_msrp'\u003E$1,029.00\u003C/span\u003E","name":"FLITE 350"},{"id":"flite_500","text":"FLITE 500\u003Cspan class='f_msrp'\u003E$1,269.00\u003C/span\u003E","name":"FLITE 500"},{"id":"flite_500_ladies","text":"FLITE 500 (Ladies)\u003Cspan class='f_msrp'\u003E$1,269.00\u003C/span\u003E","name":"FLITE 500 (Ladies)"},{"id":"flite_700","text":"FLITE 700\u003Cspan class='f_msrp'\u003E$1,649.00\u003C/span\u003E","name":"FLITE 700"},{"id":"flite_747","text":"FLITE 747\u003Cspan class='f_msrp'\u003E$1,799.00\u003C/span\u003E","name":"FLITE 747"},{"id":"flite_750","text":"FLITE 750\u003Cspan class='f_msrp'\u003E$1,999.00\u003C/span\u003E","name":"FLITE 750"},{"id":"flite_750_ladies","text":"FLITE 750 (Ladies)\u003Cspan class='f_msrp'\u003E$1,999.00\u003C/span\u003E","name":"FLITE 750 (Ladies)"},{"id":"flite_780","text":"FLITE 780\u003Cspan class='f_msrp'\u003E$4,099.00\u003C/span\u003E","name":"FLITE 780"},{"id":"flite_850","text":"FLITE 850\u003Cspan class='f_msrp'\u003E$2,919.00\u003C/span\u003E","name":"FLITE 850"},{"id":"flite_900","text":"FLITE 900\u003Cspan class='f_msrp'\u003E$3,299.00\u003C/span\u003E","name":"FLITE 900"},{"id":"flite_950","text":"FLITE 950\u003Cspan class='f_msrp'\u003E$4,919.00\u003C/span\u003E","name":"FLITE 950"},{"id":"flite_team","text":"FLITE TEAM\u003Cspan class='f_msrp'\u003E$5,969.00\u003C/span\u003E","name":"FLITE TEAM"},{"id":"green","text":"GREEN\u003Cspan class='f_msrp'\u003E$439.00\u003C/span\u003E","name":"GREEN"},{"id":"green_8","text":"GREEN 8\u003Cspan class='f_msrp'\u003E$769.00\u003C/span\u003E","name":"GREEN 8"},{"id":"green_8_dlx","text":"GREEN 8 DLX\u003Cspan class='f_msrp'\u003E$979.00\u003C/span\u003E","name":"GREEN 8 DLX"},{"id":"green_8_ladies","text":"GREEN 8 (Ladies)\u003Cspan class='f_msrp'\u003E$769.00\u003C/span\u003E","name":"GREEN 8 (Ladies)"},{"id":"green_ladies","text":"GREEN (Ladies)\u003Cspan class='f_msrp'\u003E$439.00\u003C/span\u003E","name":"GREEN (Ladies)"},{"id":"iped","text":"IPED\u003Cspan class='f_msrp'\u003E$419.00\u003C/span\u003E","name":"IPED"},{"id":"iped_3_speed","text":"IPED 3-SPEED\u003Cspan class='f_msrp'\u003E$479.00\u003C/span\u003E","name":"IPED 3-SPEED"},{"id":"k9_police","text":"K9 POLICE\u003Cspan class='f_msrp'\u003E$1,169.00\u003C/span\u003E","name":"K9 POLICE"},{"id":"latte","text":"LATTE\u003Cspan class='f_msrp'\u003E$359.00\u003C/span\u003E","name":"LATTE"},{"id":"milano","text":"MILANO\u003Cspan class='f_msrp'\u003E$1,999.00\u003C/span\u003E","name":"MILANO"},{"id":"mocha","text":"MOCHA\u003Cspan class='f_msrp'\u003E$459.00\u003C/span\u003E","name":"MOCHA"},{"id":"prescott","text":"PRESCOTT\u003Cspan class='f_msrp'\u003E$3,729.00\u003C/span\u003E","name":"PRESCOTT"},{"id":"raptor","text":"RAPTOR\u003Cspan class='f_msrp'\u003E$329.00\u003C/span\u003E","name":"RAPTOR"},{"id":"saguaro","text":"SAGUARO\u003Cspan class='f_msrp'\u003E$3,349.00\u003C/span\u003E","name":"SAGUARO"},{"id":"sixfifty_2500","text":"SIXFIFTY 2500\u003Cspan class='f_msrp'\u003E$2,149.00\u003C/span\u003E","name":"SIXFIFTY 2500"},{"id":"sixfifty_300","text":"SIXFIFTY 300\u003Cspan class='f_msrp'\u003E$689.00\u003C/span\u003E","name":"SIXFIFTY 300"},{"id":"sixfifty_300_ladies","text":"SIXFIFTY 300 (Ladies)\u003Cspan class='f_msrp'\u003E$689.00\u003C/span\u003E","name":"SIXFIFTY 300 (Ladies)"},{"id":"sixfifty_3500","text":"SIXFIFTY 3500\u003Cspan class='f_msrp'\u003E$2,799.00\u003C/span\u003E","name":"SIXFIFTY 3500"},{"id":"sixfifty_500","text":"SIXFIFTY 500\u003Cspan class='f_msrp'\u003E$889.00\u003C/span\u003E","name":"SIXFIFTY 500"},{"id":"sixfifty_500_ladies","text":"SIXFIFTY 500 (Ladies)\u003Cspan class='f_msrp'\u003E$889.00\u003C/span\u003E","name":"SIXFIFTY 500 (Ladies)"},{"id":"sixfifty_5500","text":"SIXFIFTY 5500\u003Cspan class='f_msrp'\u003E$2,399.00\u003C/span\u003E","name":"SIXFIFTY 5500"},{"id":"sixfifty_600","text":"SIXFIFTY 600\u003Cspan class='f_msrp'\u003E$1,199.00\u003C/span\u003E","name":"SIXFIFTY 600"},{"id":"sixfifty_600_ladies","text":"SIXFIFTY 600 (Ladies)\u003Cspan class='f_msrp'\u003E$1,199.00\u003C/span\u003E","name":"SIXFIFTY 600 (Ladies)"},{"id":"sixfifty_6500","text":"SIXFIFTY 6500\u003Cspan class='f_msrp'\u003E$3,099.00\u003C/span\u003E","name":"SIXFIFTY 6500"},{"id":"sixfifty_800","text":"SIXFIFTY 800\u003Cspan class='f_msrp'\u003E$2,949.00\u003C/span\u003E","name":"SIXFIFTY 800"},{"id":"sixfifty_team","text":"SIXFIFTY TEAM\u003Cspan class='f_msrp'\u003E$4,149.00\u003C/span\u003E","name":"SIXFIFTY TEAM"},{"id":"sj_100","text":"SJ 100\u003Cspan class='f_msrp'\u003E$609.00\u003C/span\u003E","name":"SJ 100"},{"id":"sj_200","text":"SJ 200\u003Cspan class='f_msrp'\u003E$769.00\u003C/span\u003E","name":"SJ 200"},{"id":"sj_24","text":"SJ 24\u003Cspan class='f_msrp'\u003E$559.00\u003C/span\u003E","name":"SJ 24"},{"id":"sj_300","text":"SJ 300\u003Cspan class='f_msrp'\u003E$899.00\u003C/span\u003E","name":"SJ 300"},{"id":"smoothie","text":"SMOOTHIE\u003Cspan class='f_msrp'\u003E$479.00\u003C/span\u003E","name":"SMOOTHIE"},{"id":"smoothie_3_speed","text":"SMOOTHIE 3-SPEED\u003Cspan class='f_msrp'\u003E$509.00\u003C/span\u003E","name":"SMOOTHIE 3-SPEED"},{"id":"smoothie_3_speed_ladies","text":"SMOOTHIE 3-SPEED (Ladies)\u003Cspan class='f_msrp'\u003E$509.00\u003C/span\u003E","name":"SMOOTHIE 3-SPEED (Ladies)"},{"id":"smoothie_ladies","text":"SMOOTHIE (Ladies)\u003Cspan class='f_msrp'\u003E$479.00\u003C/span\u003E","name":"SMOOTHIE (Ladies)"},{"id":"sport","text":"SPORT\u003Cspan class='f_msrp'\u003E$1,239.00\u003C/span\u003E","name":"SPORT"},{"id":"syntaur","text":"SYNTAUR\u003Cspan class='f_msrp'\u003E$349.00\u003C/span\u003E","name":"SYNTAUR"},{"id":"t_rex","text":"T-REX\u003Cspan class='f_msrp'\u003E$349.00\u003C/span\u003E","name":"T-REX"},{"id":"tc_100","text":"TC 100\u003Cspan class='f_msrp'\u003E$409.00\u003C/span\u003E","name":"TC 100"},{"id":"tc_100_ladies","text":"TC 100 (Ladies)\u003Cspan class='f_msrp'\u003E$409.00\u003C/span\u003E","name":"TC 100 (Ladies)"},{"id":"tc_150","text":"TC 150\u003Cspan class='f_msrp'\u003E$499.00\u003C/span\u003E","name":"TC 150"},{"id":"tc_150_ladies","text":"TC 150 (Ladies)\u003Cspan class='f_msrp'\u003E$499.00\u003C/span\u003E","name":"TC 150 (Ladies)"},{"id":"team_29","text":"TEAM 29\u003Cspan class='f_msrp'\u003E$4,799.00\u003C/span\u003E","name":"TEAM 29"},{"id":"team_29_fs","text":"Team 29 FS\u003Cspan class='f_msrp'\u003E$4,619.00\u003C/span\u003E","name":"Team 29 FS"},{"id":"tempe","text":"TEMPE\u003Cspan class='f_msrp'\u003E$1,039.00\u003C/span\u003E","name":"TEMPE"},{"id":"tr_101","text":"TR 101\u003Cspan class='f_msrp'\u003E$1,099.00\u003C/span\u003E","name":"TR 101"},{"id":"tricycle_3_speed","text":"TRICYCLE 3-SPEED\u003Cspan class='f_msrp'\u003E$769.00\u003C/span\u003E","name":"TRICYCLE 3-SPEED"},{"id":"tricycle_single_speed","text":"TRICYCLE SINGLE SPEED\u003Cspan class='f_msrp'\u003E$659.00\u003C/span\u003E","name":"TRICYCLE SINGLE SPEED"},{"id":"tucson","text":"TUCSON\u003Cspan class='f_msrp'\u003E$1,399.00\u003C/span\u003E","name":"TUCSON"},{"id":"ultra_sport_1_0","text":"ULTRA SPORT 1.0\u003Cspan class='f_msrp'\u003E$399.00\u003C/span\u003E","name":"ULTRA SPORT 1.0"},{"id":"ultra_sport_1_0_ladies","text":"ULTRA SPORT 1.0 (Ladies)","name":"ULTRA SPORT 1.0 (Ladies)"},{"id":"ultra_sport_2_0","text":"ULTRA SPORT 2.0\u003Cspan class='f_msrp'\u003E$519.00\u003C/span\u003E","name":"ULTRA SPORT 2.0"},{"id":"ultra_sport_2_0_ladies","text":"ULTRA SPORT 2.0 (Ladies)\u003Cspan class='f_msrp'\u003E$519.00\u003C/span\u003E","name":"ULTRA SPORT 2.0 (Ladies)"},{"id":"ultra_sport_3_0","text":"ULTRA SPORT 3.0\u003Cspan class='f_msrp'\u003E$659.00\u003C/span\u003E","name":"ULTRA SPORT 3.0"},{"id":"ultra_sport_3_0_ladies","text":"ULTRA SPORT 3.0 (Ladies)\u003Cspan class='f_msrp'\u003E$659.00\u003C/span\u003E","name":"ULTRA SPORT 3.0 (Ladies)"},{"id":"ultra_sport_4_0","text":"ULTRA SPORT 4.0\u003Cspan class='f_msrp'\u003E$819.00\u003C/span\u003E","name":"ULTRA SPORT 4.0"},{"id":"urban_soul","text":"URBAN SOUL\u003Cspan class='f_msrp'\u003E$439.00\u003C/span\u003E","name":"URBAN SOUL"},{"id":"urban_x","text":"URBAN X\u003Cspan class='f_msrp'\u003E$589.00\u003C/span\u003E","name":"URBAN X"},{"id":"urban_xcape","text":"URBAN XCAPE\u003Cspan class='f_msrp'\u003E$499.00\u003C/span\u003E","name":"URBAN XCAPE"},{"id":"urban_xcape_ladies","text":"URBAN XCAPE (Ladies)\u003Cspan class='f_msrp'\u003E$499.00\u003C/span\u003E","name":"URBAN XCAPE (Ladies)"},{"id":"urban_xcel","text":"URBAN XCEL\u003Cspan class='f_msrp'\u003E$769.00\u003C/span\u003E","name":"URBAN XCEL"},{"id":"urban_xpress","text":"URBAN XPRESS\u003Cspan class='f_msrp'\u003E$609.00\u003C/span\u003E","name":"URBAN XPRESS"},{"id":"urban_xpress_ladies","text":"URBAN XPRESS (Ladies)\u003Cspan class='f_msrp'\u003E$609.00\u003C/span\u003E","name":"URBAN XPRESS (Ladies)"},{"id":"urban_xtreme","text":"URBAN XTREME\u003Cspan class='f_msrp'\u003E$769.00\u003C/span\u003E","name":"URBAN XTREME"},{"id":"vitamin_a","text":"VITAMIN A\u003Cspan class='f_msrp'\u003E$479.00\u003C/span\u003E","name":"VITAMIN A"},{"id":"vitamin_a_ladies","text":"VITAMIN A (Ladies)\u003Cspan class='f_msrp'\u003E$479.00\u003C/span\u003E","name":"VITAMIN A (Ladies)"},{"id":"vitamin_b","text":"VITAMIN B\u003Cspan class='f_msrp'\u003E$599.00\u003C/span\u003E","name":"VITAMIN B"},{"id":"vitamin_b_ladies","text":"VITAMIN B (Ladies)\u003Cspan class='f_msrp'\u003E$599.00\u003C/span\u003E","name":"VITAMIN B (Ladies)"},{"id":"vitamin_c","text":"Vitamin C\u003Cspan class='f_msrp'\u003E$809.00\u003C/span\u003E","name":"Vitamin C"},{"id":"westwood","text":"WESTWOOD","name":"WESTWOOD"},{"id":"westwood_ladies","text":"WESTWOOD (Ladies)\u003Cspan class='f_msrp'\u003E$479.00\u003C/span\u003E","name":"WESTWOOD (Ladies)"},{"id":"winslow","text":"WINSLOW\u003Cspan class='f_msrp'\u003E$709.00\u003C/span\u003E","name":"WINSLOW"},{"id":"xc_104","text":"XC 104\u003Cspan class='f_msrp'\u003E$1,359.00\u003C/span\u003E","name":"XC 104"},{"id":"xc_204","text":"XC 204\u003Cspan class='f_msrp'\u003E$1,699.00\u003C/span\u003E","name":"XC 204"},{"id":"xc_204_ladies","text":"XC 204 (Ladies)\u003Cspan class='f_msrp'\u003E$1,699.00\u003C/span\u003E","name":"XC 204 (Ladies)"},{"id":"xc_team","text":"XC TEAM\u003Cspan class='f_msrp'\u003E$5,999.00\u003C/span\u003E","name":"XC TEAM"},{"id":"yuma","text":"YUMA\u003Cspan class='f_msrp'\u003E$1,799.00\u003C/span\u003E","name":"YUMA"},{"id":"zaca","text":"ZACA\u003Cspan class='f_msrp'\u003E$599.00\u003C/span\u003E","name":"ZACA"}],"2014":[{"id":"200","text":"200\u003Cspan class='f_msrp'\u003E$549.00\u003C/span\u003E","name":"200"},{"id":"2500","text":"2500\u003Cspan class='f_msrp'\u003E$2,149\u003C/span\u003E","name":"2500"},{"id":"300","text":"300\u003Cspan class='f_msrp'\u003E$659.00\u003C/span\u003E","name":"300"},{"id":"3500","text":"3500\u003Cspan class='f_msrp'\u003E$2,849\u003C/span\u003E","name":"3500"},{"id":"4_season_1000","text":"4 SEASON 1000\u003Cspan class='f_msrp'\u003E$1,299\u003C/span\u003E","name":"4 SEASON 1000"},{"id":"4_season_3000","text":"4 SEASON 3000\u003Cspan class='f_msrp'\u003E$1,799\u003C/span\u003E","name":"4 SEASON 3000"},{"id":"500","text":"500\u003Cspan class='f_msrp'\u003E$799.00\u003C/span\u003E","name":"500"},{"id":"5500","text":"5500\u003Cspan class='f_msrp'\u003E$2,499\u003C/span\u003E","name":"5500"},{"id":"600","text":"600\u003Cspan class='f_msrp'\u003E$1.10\u003C/span\u003E","name":"600"},{"id":"6500","text":"6500\u003Cspan class='f_msrp'\u003E$3,949\u003C/span\u003E","name":"6500"},{"id":"700","text":"700\u003Cspan class='f_msrp'\u003E$1,449\u003C/span\u003E","name":"700"},{"id":"7500","text":"7500\u003Cspan class='f_msrp'\u003E$5,549\u003C/span\u003E","name":"7500"},{"id":"800","text":"800\u003Cspan class='f_msrp'\u003E$2,899\u003C/span\u003E","name":"800"},{"id":"aguila","text":"AGUILA\u003Cspan class='f_msrp'\u003E$809.00\u003C/span\u003E","name":"AGUILA"},{"id":"alite","text":"ALITE\u003Cspan class='f_msrp'\u003E$1,799\u003C/span\u003E","name":"ALITE"},{"id":"alite_150","text":"ALITE 150\u003Cspan class='f_msrp'\u003E$489.00\u003C/span\u003E","name":"ALITE 150"},{"id":"alite_24","text":"ALITE 24\u003Cspan class='f_msrp'\u003E$549.00\u003C/span\u003E","name":"ALITE 24"},{"id":"alite_350","text":"ALITE 350\u003Cspan class='f_msrp'\u003E$579.00\u003C/span\u003E","name":"ALITE 350"},{"id":"alite_40","text":"ALITE 40\u003Cspan class='f_msrp'\u003E$329.00\u003C/span\u003E","name":"ALITE 40"},{"id":"alite_500","text":"ALITE 500\u003Cspan class='f_msrp'\u003E$739.00\u003C/span\u003E","name":"ALITE 500"},{"id":"bajada","text":"BAJADA\u003Cspan class='f_msrp'\u003E$1,749\u003C/span\u003E","name":"BAJADA"},{"id":"brentwood","text":"BRENTWOOD\u003Cspan class='f_msrp'\u003E$399.00\u003C/span\u003E","name":"BRENTWOOD"},{"id":"cross","text":"CROSS\u003Cspan class='f_msrp'\u003E$1,799\u003C/span\u003E","name":"CROSS"},{"id":"cx_100","text":"CX 100\u003Cspan class='f_msrp'\u003E$1,399\u003C/span\u003E","name":"CX 100"},{"id":"cx_300","text":"CX 300\u003Cspan class='f_msrp'\u003E$2,199\u003C/span\u003E","name":"CX 300"},{"id":"dh_650","text":"DH 650\u003Cspan class='f_msrp'\u003E$6,299\u003C/span\u003E","name":"DH 650"},{"id":"dj_24","text":"DJ 24\u003Cspan class='f_msrp'\u003E$609.00\u003C/span\u003E","name":"DJ 24"},{"id":"dj_50","text":"DJ 50\u003Cspan class='f_msrp'\u003E$699.00\u003C/span\u003E","name":"DJ 50"},{"id":"f20a_h7","text":"F20A-H7\u003Cspan class='f_msrp'\u003E$519.00\u003C/span\u003E","name":"F20A-H7"},{"id":"flagstaff","text":"FLAGSTAFF\u003Cspan class='f_msrp'\u003E$2,449\u003C/span\u003E","name":"FLAGSTAFF"},{"id":"flite_100","text":"FLITE 100\u003Cspan class='f_msrp'\u003E$659.00\u003C/span\u003E","name":"FLITE 100"},{"id":"flite_150","text":"FLITE 150\u003Cspan class='f_msrp'\u003E$579.00\u003C/span\u003E","name":"FLITE 150"},{"id":"flite_223","text":"FLITE 223\u003Cspan class='f_msrp'\u003E$659.00\u003C/span\u003E","name":"FLITE 223"},{"id":"flite_280","text":"FLITE 280\u003Cspan class='f_msrp'\u003E$659.00\u003C/span\u003E","name":"FLITE 280"},{"id":"flite_300","text":"FLITE 300\u003Cspan class='f_msrp'\u003E$789.00\u003C/span\u003E","name":"FLITE 300"},{"id":"flite_500","text":"FLITE 500\u003Cspan class='f_msrp'\u003E$1,399\u003C/span\u003E","name":"FLITE 500"},{"id":"flite_747","text":"FLITE 747\u003Cspan class='f_msrp'\u003E$1,799\u003C/span\u003E","name":"FLITE 747"},{"id":"flite_750","text":"FLITE 750\u003Cspan class='f_msrp'\u003E$1,849\u003C/span\u003E","name":"FLITE 750"},{"id":"flite_780","text":"FLITE 780\u003Cspan class='f_msrp'\u003E$3,799\u003C/span\u003E","name":"FLITE 780"},{"id":"flite_850","text":"FLITE 850\u003Cspan class='f_msrp'\u003E$2,699\u003C/span\u003E","name":"FLITE 850"},{"id":"flite_900","text":"FLITE 900\u003Cspan class='f_msrp'\u003E$3,449\u003C/span\u003E","name":"FLITE 900"},{"id":"flite_team","text":"FLITE TEAM\u003Cspan class='f_msrp'\u003E$6,099\u003C/span\u003E","name":"FLITE TEAM"},{"id":"green_1","text":"GREEN 1\u003Cspan class='f_msrp'\u003E$349.00\u003C/span\u003E","name":"GREEN 1"},{"id":"green_3","text":"GREEN 3\u003Cspan class='f_msrp'\u003E$439.00\u003C/span\u003E","name":"GREEN 3"},{"id":"green_8","text":"GREEN 8\u003Cspan class='f_msrp'\u003E$769.00\u003C/span\u003E","name":"GREEN 8"},{"id":"green_8_deluxe","text":"GREEN 8 DELUXE\u003Cspan class='f_msrp'\u003E$979.00\u003C/span\u003E","name":"GREEN 8 DELUXE"},{"id":"green_8e","text":"GREEN 8e\u003Cspan class='f_msrp'\u003E$489.00\u003C/span\u003E","name":"GREEN 8e"},{"id":"hot_rod","text":"HOT ROD\u003Cspan class='f_msrp'\u003E$329.00\u003C/span\u003E","name":"HOT ROD"},{"id":"iped_iped3","text":"IPED, IPED3\u003Cspan class='f_msrp'\u003E$iPed 419, iPed3 479\u003C/span\u003E","name":"IPED, IPED3"},{"id":"k9_police","text":"K9 POLICE\u003Cspan class='f_msrp'\u003E$1,099\u003C/span\u003E","name":"K9 POLICE"},{"id":"latte","text":"LATTE\u003Cspan class='f_msrp'\u003E$359.00\u003C/span\u003E","name":"LATTE"},{"id":"milano","text":"MILANO\u003Cspan class='f_msrp'\u003E$1,999\u003C/span\u003E","name":"MILANO"},{"id":"mocha","text":"MOCHA\u003Cspan class='f_msrp'\u003E$459.00\u003C/span\u003E","name":"MOCHA"},{"id":"prescott","text":"PRESCOTT\u003Cspan class='f_msrp'\u003E$3,749\u003C/span\u003E","name":"PRESCOTT"},{"id":"raptor","text":"RAPTOR\u003Cspan class='f_msrp'\u003E$329.00\u003C/span\u003E","name":"RAPTOR"},{"id":"saguaro","text":"SAGUARO\u003Cspan class='f_msrp'\u003E$3,049\u003C/span\u003E","name":"SAGUARO"},{"id":"sj_100","text":"SJ 100\u003Cspan class='f_msrp'\u003E$629.00\u003C/span\u003E","name":"SJ 100"},{"id":"sj_200","text":"SJ 200\u003Cspan class='f_msrp'\u003E$829.00\u003C/span\u003E","name":"SJ 200"},{"id":"sj_24","text":"SJ 24\u003Cspan class='f_msrp'\u003E$579.00\u003C/span\u003E","name":"SJ 24"},{"id":"smoothie","text":"SMOOTHIE\u003Cspan class='f_msrp'\u003E$489.00\u003C/span\u003E","name":"SMOOTHIE"},{"id":"smoothie_3_speed","text":"SMOOTHIE 3-SPEED\u003Cspan class='f_msrp'\u003E$519.00\u003C/span\u003E","name":"SMOOTHIE 3-SPEED"},{"id":"soul","text":"SOUL\u003Cspan class='f_msrp'\u003E$439.00\u003C/span\u003E","name":"SOUL"},{"id":"sport","text":"SPORT\u003Cspan class='f_msrp'\u003E$1,239\u003C/span\u003E","name":"SPORT"},{"id":"syntaur","text":"SYNTAUR\u003Cspan class='f_msrp'\u003E$349.00\u003C/span\u003E","name":"SYNTAUR"},{"id":"t_rex","text":"T-REX\u003Cspan class='f_msrp'\u003E$349.00\u003C/span\u003E","name":"T-REX"},{"id":"tc_100","text":"TC 100\u003Cspan class='f_msrp'\u003E$419.00\u003C/span\u003E","name":"TC 100"},{"id":"tc_150","text":"TC 150\u003Cspan class='f_msrp'\u003E$499.00\u003C/span\u003E","name":"TC 150"},{"id":"team_29","text":"TEAM 29\u003Cspan class='f_msrp'\u003E$4,799\u003C/span\u003E","name":"TEAM 29"},{"id":"team_29_fs","text":"TEAM 29 FS\u003Cspan class='f_msrp'\u003E$4,619\u003C/span\u003E","name":"TEAM 29 FS"},{"id":"team_650","text":"TEAM 650\u003Cspan class='f_msrp'\u003E$4,599\u003C/span\u003E","name":"TEAM 650"},{"id":"tempe","text":"TEMPE\u003Cspan class='f_msrp'\u003E$1,099\u003C/span\u003E","name":"TEMPE"},{"id":"tr_101","text":"TR 101\u003Cspan class='f_msrp'\u003E$1,099\u003C/span\u003E","name":"TR 101"},{"id":"trike","text":"TRIKE\u003Cspan class='f_msrp'\u003E$659.00\u003C/span\u003E","name":"TRIKE"},{"id":"trike_3speed","text":"TRIKE 3SPEED\u003Cspan class='f_msrp'\u003E$769.00\u003C/span\u003E","name":"TRIKE 3SPEED"},{"id":"tucson","text":"TUCSON\u003Cspan class='f_msrp'\u003E$1,449\u003C/span\u003E","name":"TUCSON"},{"id":"ultrasport_1_0","text":"ULTRASPORT 1.0\u003Cspan class='f_msrp'\u003E$439.00\u003C/span\u003E","name":"ULTRASPORT 1.0"},{"id":"ultrasport_2_0","text":"ULTRASPORT 2.0\u003Cspan class='f_msrp'\u003E$549.00\u003C/span\u003E","name":"ULTRASPORT 2.0"},{"id":"ultrasport_3_0","text":"ULTRASPORT 3.0\u003Cspan class='f_msrp'\u003E$659.00\u003C/span\u003E","name":"ULTRASPORT 3.0"},{"id":"ultrasport_4_0","text":"ULTRASPORT 4.0\u003Cspan class='f_msrp'\u003E$919.00\u003C/span\u003E","name":"ULTRASPORT 4.0"},{"id":"urban_x","text":"URBAN X\u003Cspan class='f_msrp'\u003E$589.00\u003C/span\u003E","name":"URBAN X"},{"id":"vitamin_a","text":"VITAMIN A\u003Cspan class='f_msrp'\u003E$479.00\u003C/span\u003E","name":"VITAMIN A"},{"id":"vitamin_b","text":"VITAMIN B\u003Cspan class='f_msrp'\u003E$599.00\u003C/span\u003E","name":"VITAMIN B"},{"id":"vitamin_c","text":"VITAMIN C\u003Cspan class='f_msrp'\u003E$979.00\u003C/span\u003E","name":"VITAMIN C"},{"id":"westwood","text":"WESTWOOD\u003Cspan class='f_msrp'\u003E$489.00\u003C/span\u003E","name":"WESTWOOD"},{"id":"winslow","text":"WINSLOW\u003Cspan class='f_msrp'\u003E$659.00\u003C/span\u003E","name":"WINSLOW"},{"id":"xcape","text":"XCAPE\u003Cspan class='f_msrp'\u003E$499.00\u003C/span\u003E","name":"XCAPE"},{"id":"xcel","text":"XCEL\u003Cspan class='f_msrp'\u003E$729.00\u003C/span\u003E","name":"XCEL"},{"id":"xpress","text":"XPRESS\u003Cspan class='f_msrp'\u003E$619.00\u003C/span\u003E","name":"XPRESS"},{"id":"xtreme","text":"XTREME\u003Cspan class='f_msrp'\u003E$869.00\u003C/span\u003E","name":"XTREME"},{"id":"zaca","text":"ZACA\u003Cspan class='f_msrp'\u003E$549.00\u003C/span\u003E","name":"ZACA"}]}