{"bike":{"frame_model":"TCX 1","manufacturer":"Giant","year":2013,"description":"ALUXX SL-Grade Aluminum w/ Eyelets","original_paints":["Black/Blue/White"],"sizes":["S, M, M/L, L, XL"],"msrp":"$1,850","stock_image":"https://bikebook.s3.amazonaws.com/uploads/Fr/7481/TCX_1_v1.jpg"},"components":[{"ctype":"fork","description":"Advanced-Grade Composite, Alloy OverDrive Steerer"},{"ctype":"handlebars","description":"Giant Connect SL, 31.8"},{"ctype":"stem","description":"Giant Connect SL"},{"ctype":"seatpost","description":"Giant Connect SL, Composite, 30.9"},{"ctype":"saddle","description":"Giant Performance Road, Men's"},{"ctype":"shifter","description":"SRAM Rival","front_or_rear":"both"},{"ctype":"derailleur","description":"SRAM Rival","front_or_rear":"front"},{"ctype":"derailleur","description":"SRAM Rival","front_or_rear":"rear"},{"ctype":"brake","description":"TRP CX","front_or_rear":"both"},{"ctype":"brake lever","description":"SRAM Rival w/ Tektro RL721 Top Bar Levers","front_or_rear":"both"},{"ctype":"cog/cassette/freewheel","description":"SRAM PG-1050 11x28, 10-Speed"},{"ctype":"chain","description":"KMC X10"},{"ctype":"crankset","description":"SRAM Rival, 38/46"},{"ctype":"bottom bracket","description":"SRAM GXP, Press Fit"},{"ctype":"rim","description":"Giant P-R2, Double Wall","front_or_rear":"both"},{"ctype":"hub","description":"Giant Sealed Bearing, 24/28h","front_or_rear":"both"},{"ctype":"spokes","description":"DT Swiss Competition, 14/15g"},{"ctype":"tire","description":"Kenda Slant 6, 700x32, Folding","front_or_rear":"both"},{"ctype":"other","description":"2 Sets of Water-Bottle Bolts"},{"ctype":"weight","description":"The most accurate way to determine any bike’s weight is to have your local dealer weigh it for you. Many brands strive to list the lowest possible weight, but in reality weight can vary based on size, finish, hardware and accessories. All Giant bikes are designed for best-in-class weight and ride quality."}]}