{"bike":{"frame_model":"Trance X 29er 0","manufacturer":"Giant","year":2013,"description":"ALUXX SL-Grade Aluminum, 5\" Maestro Suspension","original_msrp":"$4,250","paint_description":"White/Polished Aluminum/Blue","rear_wheel_size":622,"stock_photo_url":"https://bikebook.s3.amazonaws.com/uploads/Fr/7497/Trance_X_29er_0_retouch_72dpiWIDE.jpg","rear_tire_narrow":true},"components":[{"component_type":"fork","description":"Fox 32 Float 29 FIT CTD w/ 15QR thru-axle, OverDrive 2, 120mm Travel"},{"component_type":"rear suspension","description":"Fox Float CTD Boostvalve"},{"component_type":"handlebar","description":"Giant Contact TR, Low Rise, 31.8"},{"component_type":"stem","description":"Giant Contact w/ Titanium hardware, OverDrive 2"},{"component_type":"seatpost","description":"Giant Contact Switch w/ Remote, 30.9"},{"component_type":"saddle","description":"Fi'zi:k Gobi XM w/ Manganese Rails"},{"component_type":"shifter","description":"Shimano Deore XT, 2x10 Speed","front_or_rear":"both"},{"component_type":"derailleur","description":"Shimano Deore XT","front_or_rear":"front"},{"component_type":"derailleur","description":"Shimano Deore XT Shadow Plus","front_or_rear":"rear"},{"component_type":"brake","description":"Shimano Deore XT, [F] 180mm, [R] 160mm","front_or_rear":"both"},{"component_type":"brake lever","description":"Shimano Deore XT","front_or_rear":"both"},{"component_type":"cog/cassette/freewheel","description":"Shimano HG81 11x36, 10-Speed"},{"component_type":"chain","description":"KMC X10"},{"component_type":"crankset","description":"Shimano Deore XT, 24/38"},{"component_type":"bottom bracket","description":"Shimano, Press Fit"},{"component_type":"rim","description":"Giant P-TRX 29er 1 WheelSystem","front_or_rear":"both"},{"component_type":"hub","description":"Giant P-TRX 29er 1 WheelSystem","front_or_rear":"both"},{"component_type":"spokes","description":"Giant P-TRX 29er 1 WheelSystem"},{"component_type":"tire","description":"Schwalbe Nobby Nic, 29x2.25 TL Ready Evolution Folding","front_or_rear":"both"}]}